[{"geoid":"22001","geo_population":57674,"geo_population_d1_native":13,"geo_population_d1_asian":95,"geo_population_d1_black":9511,"geo_population_d1_hispanic":1780,"geo_population_d1_pi":0,"geo_population_d1_two":1822,"geo_population_d1_white":44413,"geo_population_d1_unk":40,"geo_population_d2_male":28596,"geo_population_d2_female":29078,"geo_medincome":44977,"geo_households":14558,"geo_pctba":0.137,"metric190_d1_native":0,"metric190_d1_asian":0,"metric190_d1_black":0.25,"metric190_d1_hispanic":0.05,"metric190_d1_pi":0,"metric190_d1_two":0.05,"metric190_d1_white":0.64,"metric190_d1_unk":0,"metric50_d7_less_than_10k":0.012,"metric50_d7_10k_to_15k":0.046,"metric50_d7_15k_to_25k":0.125,"metric50_d7_25k_to_35k":0.155,"metric50_d7_35k_to_50k":0.223,"metric50_d7_50k_to_65k":0.136,"metric50_d7_65k_to_75k":0.074,"metric50_d7_75k_to_100k":0.113,"metric50_d7_more_than_100k":0.117},{"geoid":"22003","geo_population":22798,"geo_population_d1_native":371,"geo_population_d1_asian":164,"geo_population_d1_black":3962,"geo_population_d1_hispanic":1460,"geo_population_d1_pi":0,"geo_population_d1_two":858,"geo_population_d1_white":15964,"geo_population_d1_unk":19,"geo_population_d2_male":12751,"geo_population_d2_female":10047,"geo_medincome":52755,"geo_households":5370,"geo_pctba":0.1205,"metric190_d1_native":0.01,"metric190_d1_asian":0,"metric190_d1_black":0.18,"metric190_d1_hispanic":0.02,"metric190_d1_pi":0,"metric190_d1_two":0.06,"metric190_d1_white":0.72,"metric190_d1_unk":0,"metric50_d7_less_than_10k":0.029,"metric50_d7_10k_to_15k":0.03,"metric50_d7_15k_to_25k":0.147,"metric50_d7_25k_to_35k":0.149,"metric50_d7_35k_to_50k":0.206,"metric50_d7_50k_to_65k":0.128,"metric50_d7_65k_to_75k":0.047,"metric50_d7_75k_to_100k":0.115,"metric50_d7_more_than_100k":0.148},{"geoid":"22005","geo_population":126973,"geo_population_d1_native":251,"geo_population_d1_asian":1428,"geo_population_d1_black":28849,"geo_population_d1_hispanic":7829,"geo_population_d1_pi":97,"geo_population_d1_two":3604,"geo_population_d1_white":84232,"geo_population_d1_unk":683,"geo_population_d2_male":62764,"geo_population_d2_female":64209,"geo_medincome":93800,"geo_households":34448,"geo_pctba":0.2903,"metric190_d1_native":0,"metric190_d1_asian":0.01,"metric190_d1_black":0.31,"metric190_d1_hispanic":0.12,"metric190_d1_pi":0,"metric190_d1_two":0.04,"metric190_d1_white":0.51,"metric190_d1_unk":0,"metric50_d7_less_than_10k":0.014,"metric50_d7_10k_to_15k":0.02,"metric50_d7_15k_to_25k":0.067,"metric50_d7_25k_to_35k":0.113,"metric50_d7_35k_to_50k":0.138,"metric50_d7_50k_to_65k":0.16,"metric50_d7_65k_to_75k":0.082,"metric50_d7_75k_to_100k":0.145,"metric50_d7_more_than_100k":0.261},{"geoid":"22007","geo_population":21067,"geo_population_d1_native":98,"geo_population_d1_asian":88,"geo_population_d1_black":6091,"geo_population_d1_hispanic":714,"geo_population_d1_pi":0,"geo_population_d1_two":346,"geo_population_d1_white":13714,"geo_population_d1_unk":16,"geo_population_d2_male":10039,"geo_population_d2_female":11028,"geo_medincome":47023,"geo_households":5561,"geo_pctba":0.1344,"metric190_d1_native":0,"metric190_d1_asian":0.01,"metric190_d1_black":0.38,"metric190_d1_hispanic":0.06,"metric190_d1_pi":0,"metric190_d1_two":0.02,"metric190_d1_white":0.53,"metric190_d1_unk":0,"metric50_d7_less_than_10k":0.009,"metric50_d7_10k_to_15k":0.049,"metric50_d7_15k_to_25k":0.075,"metric50_d7_25k_to_35k":0.133,"metric50_d7_35k_to_50k":0.227,"metric50_d7_50k_to_65k":0.15,"metric50_d7_65k_to_75k":0.086,"metric50_d7_75k_to_100k":0.118,"metric50_d7_more_than_100k":0.154},{"geoid":"22009","geo_population":39529,"geo_population_d1_native":304,"geo_population_d1_asian":251,"geo_population_d1_black":10079,"geo_population_d1_hispanic":870,"geo_population_d1_pi":12,"geo_population_d1_two":2497,"geo_population_d1_white":25469,"geo_population_d1_unk":47,"geo_population_d2_male":19774,"geo_population_d2_female":19755,"geo_medincome":38696,"geo_households":9099,"geo_pctba":0.1228,"metric190_d1_native":0.01,"metric190_d1_asian":0.01,"metric190_d1_black":0.42,"metric190_d1_hispanic":0.01,"metric190_d1_pi":0,"metric190_d1_two":0.05,"metric190_d1_white":0.5,"metric190_d1_unk":0,"metric50_d7_less_than_10k":0.06,"metric50_d7_10k_to_15k":0.053,"metric50_d7_15k_to_25k":0.155,"metric50_d7_25k_to_35k":0.162,"metric50_d7_35k_to_50k":0.215,"metric50_d7_50k_to_65k":0.104,"metric50_d7_65k_to_75k":0.087,"metric50_d7_75k_to_100k":0.083,"metric50_d7_more_than_100k":0.082},{"geoid":"22011","geo_population":36553,"geo_population_d1_native":60,"geo_population_d1_asian":242,"geo_population_d1_black":4148,"geo_population_d1_hispanic":1448,"geo_population_d1_pi":13,"geo_population_d1_two":1458,"geo_population_d1_white":28938,"geo_population_d1_unk":246,"geo_population_d2_male":18747,"geo_population_d2_female":17806,"geo_medincome":68525,"geo_households":9622,"geo_pctba":0.1788,"metric190_d1_native":0,"metric190_d1_asian":0,"metric190_d1_black":0.1,"metric190_d1_hispanic":0.05,"metric190_d1_pi":0,"metric190_d1_two":0.06,"metric190_d1_white":0.77,"metric190_d1_unk":0,"metric50_d7_less_than_10k":0.017,"metric50_d7_10k_to_15k":0.021,"metric50_d7_15k_to_25k":0.098,"metric50_d7_25k_to_35k":0.123,"metric50_d7_35k_to_50k":0.135,"metric50_d7_50k_to_65k":0.136,"metric50_d7_65k_to_75k":0.113,"metric50_d7_75k_to_100k":0.122,"metric50_d7_more_than_100k":0.235},{"geoid":"22013","geo_population":12958,"geo_population_d1_native":28,"geo_population_d1_asian":5,"geo_population_d1_black":5396,"geo_population_d1_hispanic":285,"geo_population_d1_pi":0,"geo_population_d1_two":246,"geo_population_d1_white":6933,"geo_population_d1_unk":65,"geo_population_d2_male":6192,"geo_population_d2_female":6766,"geo_medincome":34268,"geo_households":3090,"geo_pctba":0.1238,"metric190_d1_native":0,"metric190_d1_asian":0.01,"metric190_d1_black":0.48,"metric190_d1_hispanic":0.02,"metric190_d1_pi":0,"metric190_d1_two":0.03,"metric190_d1_white":0.46,"metric190_d1_unk":0,"metric50_d7_less_than_10k":0.003,"metric50_d7_10k_to_15k":0.065,"metric50_d7_15k_to_25k":0.208,"metric50_d7_25k_to_35k":0.199,"metric50_d7_35k_to_50k":0.178,"metric50_d7_50k_to_65k":0.13,"metric50_d7_65k_to_75k":0.031,"metric50_d7_75k_to_100k":0.078,"metric50_d7_more_than_100k":0.108},{"geoid":"22015","geo_population":128877,"geo_population_d1_native":447,"geo_population_d1_asian":2524,"geo_population_d1_black":30369,"geo_population_d1_hispanic":8914,"geo_population_d1_pi":9,"geo_population_d1_two":3739,"geo_population_d1_white":82536,"geo_population_d1_unk":339,"geo_population_d2_male":64006,"geo_population_d2_female":64871,"geo_medincome":64598,"geo_households":31653,"geo_pctba":0.2757,"metric190_d1_native":0,"metric190_d1_asian":0.02,"metric190_d1_black":0.29,"metric190_d1_hispanic":0.12,"metric190_d1_pi":0,"metric190_d1_two":0.04,"metric190_d1_white":0.52,"metric190_d1_unk":0,"metric50_d7_less_than_10k":0.01,"metric50_d7_10k_to_15k":0.033,"metric50_d7_15k_to_25k":0.134,"metric50_d7_25k_to_35k":0.13,"metric50_d7_35k_to_50k":0.168,"metric50_d7_50k_to_65k":0.166,"metric50_d7_65k_to_75k":0.082,"metric50_d7_75k_to_100k":0.129,"metric50_d7_more_than_100k":0.148},{"geoid":"22017","geo_population":236259,"geo_population_d1_native":661,"geo_population_d1_asian":2990,"geo_population_d1_black":116167,"geo_population_d1_hispanic":7200,"geo_population_d1_pi":134,"geo_population_d1_two":6034,"geo_population_d1_white":102807,"geo_population_d1_unk":266,"geo_population_d2_male":112058,"geo_population_d2_female":124201,"geo_medincome":47572,"geo_households":56240,"geo_pctba":0.2429,"metric190_d1_native":0,"metric190_d1_asian":0.01,"metric190_d1_black":0.64,"metric190_d1_hispanic":0.05,"metric190_d1_pi":0,"metric190_d1_two":0.03,"metric190_d1_white":0.26,"metric190_d1_unk":0,"metric50_d7_less_than_10k":0.027,"metric50_d7_10k_to_15k":0.041,"metric50_d7_15k_to_25k":0.127,"metric50_d7_25k_to_35k":0.162,"metric50_d7_35k_to_50k":0.187,"metric50_d7_50k_to_65k":0.16,"metric50_d7_65k_to_75k":0.063,"metric50_d7_75k_to_100k":0.105,"metric50_d7_more_than_100k":0.128},{"geoid":"22019","geo_population":210770,"geo_population_d1_native":347,"geo_population_d1_asian":3092,"geo_population_d1_black":51769,"geo_population_d1_hispanic":8823,"geo_population_d1_pi":56,"geo_population_d1_two":6030,"geo_population_d1_white":139663,"geo_population_d1_unk":990,"geo_population_d2_male":103638,"geo_population_d2_female":107132,"geo_medincome":64370,"geo_households":50249,"geo_pctba":0.2355,"metric190_d1_native":0,"metric190_d1_asian":0.02,"metric190_d1_black":0.32,"metric190_d1_hispanic":0.08,"metric190_d1_pi":0,"metric190_d1_two":0.04,"metric190_d1_white":0.54,"metric190_d1_unk":0,"metric50_d7_less_than_10k":0.021,"metric50_d7_10k_to_15k":0.041,"metric50_d7_15k_to_25k":0.126,"metric50_d7_25k_to_35k":0.123,"metric50_d7_35k_to_50k":0.169,"metric50_d7_50k_to_65k":0.14,"metric50_d7_65k_to_75k":0.073,"metric50_d7_75k_to_100k":0.108,"metric50_d7_more_than_100k":0.2},{"geoid":"22021","geo_population":9658,"geo_population_d1_native":0,"geo_population_d1_asian":7,"geo_population_d1_black":1957,"geo_population_d1_hispanic":82,"geo_population_d1_pi":0,"geo_population_d1_two":168,"geo_population_d1_white":7431,"geo_population_d1_unk":13,"geo_population_d2_male":5100,"geo_population_d2_female":4558,"geo_medincome":45707,"geo_households":2449,"geo_pctba":0.1205,"metric190_d1_native":0,"metric190_d1_asian":0,"metric190_d1_black":0.16,"metric190_d1_hispanic":0.03,"metric190_d1_pi":0,"metric190_d1_two":0.03,"metric190_d1_white":0.79,"metric190_d1_unk":0,"metric50_d7_less_than_10k":0.069,"metric50_d7_10k_to_15k":0.034,"metric50_d7_15k_to_25k":0.1,"metric50_d7_25k_to_35k":0.1,"metric50_d7_35k_to_50k":0.303,"metric50_d7_50k_to_65k":0.076,"metric50_d7_65k_to_75k":0.065,"metric50_d7_75k_to_100k":0.152,"metric50_d7_more_than_100k":0.1},{"geoid":"22023","geo_population":5447,"geo_population_d1_native":128,"geo_population_d1_asian":50,"geo_population_d1_black":60,"geo_population_d1_hispanic":218,"geo_population_d1_pi":0,"geo_population_d1_two":243,"geo_population_d1_white":4747,"geo_population_d1_unk":1,"geo_population_d2_male":2989,"geo_population_d2_female":2458,"geo_medincome":69847,"geo_households":1802,"geo_pctba":0.144,"metric190_d1_native":0,"metric190_d1_asian":0,"metric190_d1_black":0.01,"metric190_d1_hispanic":0.08,"metric190_d1_pi":0,"metric190_d1_two":0.02,"metric190_d1_white":0.88,"metric190_d1_unk":0,"metric50_d7_less_than_10k":0,"metric50_d7_10k_to_15k":0.009,"metric50_d7_15k_to_25k":0.058,"metric50_d7_25k_to_35k":0.119,"metric50_d7_35k_to_50k":0.218,"metric50_d7_50k_to_65k":0.099,"metric50_d7_65k_to_75k":0.174,"metric50_d7_75k_to_100k":0.162,"metric50_d7_more_than_100k":0.161},{"geoid":"22025","geo_population":8895,"geo_population_d1_native":10,"geo_population_d1_asian":7,"geo_population_d1_black":2806,"geo_population_d1_hispanic":97,"geo_population_d1_pi":0,"geo_population_d1_two":89,"geo_population_d1_white":5886,"geo_population_d1_unk":0,"geo_population_d2_male":4655,"geo_population_d2_female":4240,"geo_medincome":48259,"geo_households":2221,"geo_pctba":0.1756,"metric190_d1_native":0,"metric190_d1_asian":0,"metric190_d1_black":0.36,"metric190_d1_hispanic":0.01,"metric190_d1_pi":0,"metric190_d1_two":0.03,"metric190_d1_white":0.59,"metric190_d1_unk":0,"metric50_d7_less_than_10k":0.074,"metric50_d7_10k_to_15k":0.024,"metric50_d7_15k_to_25k":0.133,"metric50_d7_25k_to_35k":0.186,"metric50_d7_35k_to_50k":0.2,"metric50_d7_50k_to_65k":0.096,"metric50_d7_65k_to_75k":0.117,"metric50_d7_75k_to_100k":0.072,"metric50_d7_more_than_100k":0.098},{"geoid":"22027","geo_population":14203,"geo_population_d1_native":2,"geo_population_d1_asian":19,"geo_population_d1_black":7028,"geo_population_d1_hispanic":253,"geo_population_d1_pi":0,"geo_population_d1_two":432,"geo_population_d1_white":6469,"geo_population_d1_unk":0,"geo_population_d2_male":7656,"geo_population_d2_female":6547,"geo_medincome":32034,"geo_households":2971,"geo_pctba":0.1165,"metric190_d1_native":0,"metric190_d1_asian":0.01,"metric190_d1_black":0.67,"metric190_d1_hispanic":0.02,"metric190_d1_pi":0,"metric190_d1_two":0.03,"metric190_d1_white":0.28,"metric190_d1_unk":0,"metric50_d7_less_than_10k":0.01,"metric50_d7_10k_to_15k":0.06,"metric50_d7_15k_to_25k":0.332,"metric50_d7_25k_to_35k":0.219,"metric50_d7_35k_to_50k":0.107,"metric50_d7_50k_to_65k":0.097,"metric50_d7_65k_to_75k":0.049,"metric50_d7_75k_to_100k":0.05,"metric50_d7_more_than_100k":0.077},{"geoid":"22029","geo_population":18677,"geo_population_d1_native":17,"geo_population_d1_asian":63,"geo_population_d1_black":7316,"geo_population_d1_hispanic":355,"geo_population_d1_pi":0,"geo_population_d1_two":271,"geo_population_d1_white":10645,"geo_population_d1_unk":10,"geo_population_d2_male":9298,"geo_population_d2_female":9379,"geo_medincome":38929,"geo_households":3950,"geo_pctba":0.1756,"metric190_d1_native":0,"metric190_d1_asian":0.01,"metric190_d1_black":0.45,"metric190_d1_hispanic":0.03,"metric190_d1_pi":0,"metric190_d1_two":0.02,"metric190_d1_white":0.49,"metric190_d1_unk":0,"metric50_d7_less_than_10k":0.042,"metric50_d7_10k_to_15k":0.037,"metric50_d7_15k_to_25k":0.12,"metric50_d7_25k_to_35k":0.285,"metric50_d7_35k_to_50k":0.243,"metric50_d7_50k_to_65k":0.09,"metric50_d7_65k_to_75k":0.046,"metric50_d7_75k_to_100k":0.064,"metric50_d7_more_than_100k":0.074},{"geoid":"22031","geo_population":26821,"geo_population_d1_native":137,"geo_population_d1_asian":73,"geo_population_d1_black":9164,"geo_population_d1_hispanic":879,"geo_population_d1_pi":0,"geo_population_d1_two":690,"geo_population_d1_white":15852,"geo_population_d1_unk":26,"geo_population_d2_male":13130,"geo_population_d2_female":13691,"geo_medincome":49807,"geo_households":7130,"geo_pctba":0.1632,"metric190_d1_native":0,"metric190_d1_asian":0.01,"metric190_d1_black":0.38,"metric190_d1_hispanic":0.05,"metric190_d1_pi":0,"metric190_d1_two":0.04,"metric190_d1_white":0.52,"metric190_d1_unk":0,"metric50_d7_less_than_10k":0.03,"metric50_d7_10k_to_15k":0.046,"metric50_d7_15k_to_25k":0.162,"metric50_d7_25k_to_35k":0.107,"metric50_d7_35k_to_50k":0.176,"metric50_d7_50k_to_65k":0.144,"metric50_d7_65k_to_75k":0.083,"metric50_d7_75k_to_100k":0.14,"metric50_d7_more_than_100k":0.111},{"geoid":"22033","geo_population":454369,"geo_population_d1_native":469,"geo_population_d1_asian":14077,"geo_population_d1_black":204823,"geo_population_d1_hispanic":20482,"geo_population_d1_pi":0,"geo_population_d1_two":15479,"geo_population_d1_white":197541,"geo_population_d1_unk":1498,"geo_population_d2_male":217767,"geo_population_d2_female":236602,"geo_medincome":62083,"geo_households":102601,"geo_pctba":0.3818,"metric190_d1_native":0,"metric190_d1_asian":0.03,"metric190_d1_black":0.62,"metric190_d1_hispanic":0.11,"metric190_d1_pi":0,"metric190_d1_two":0.02,"metric190_d1_white":0.22,"metric190_d1_unk":0,"metric50_d7_less_than_10k":0.02,"metric50_d7_10k_to_15k":0.028,"metric50_d7_15k_to_25k":0.103,"metric50_d7_25k_to_35k":0.137,"metric50_d7_35k_to_50k":0.172,"metric50_d7_50k_to_65k":0.151,"metric50_d7_65k_to_75k":0.083,"metric50_d7_75k_to_100k":0.114,"metric50_d7_more_than_100k":0.19},{"geoid":"22035","geo_population":7371,"geo_population_d1_native":50,"geo_population_d1_asian":0,"geo_population_d1_black":4891,"geo_population_d1_hispanic":110,"geo_population_d1_pi":0,"geo_population_d1_two":248,"geo_population_d1_white":2037,"geo_population_d1_unk":35,"geo_population_d2_male":4122,"geo_population_d2_female":3249,"geo_medincome":30856,"geo_households":1525,"geo_pctba":0.1179,"metric190_d1_native":0,"metric190_d1_asian":0,"metric190_d1_black":0.99,"metric190_d1_hispanic":0,"metric190_d1_pi":0,"metric190_d1_two":0,"metric190_d1_white":0.01,"metric190_d1_unk":0,"metric50_d7_less_than_10k":0.01,"metric50_d7_10k_to_15k":0.118,"metric50_d7_15k_to_25k":0.184,"metric50_d7_25k_to_35k":0.245,"metric50_d7_35k_to_50k":0.157,"metric50_d7_50k_to_65k":0.053,"metric50_d7_65k_to_75k":0.052,"metric50_d7_75k_to_100k":0.109,"metric50_d7_more_than_100k":0.071},{"geoid":"22037","geo_population":19452,"geo_population_d1_native":152,"geo_population_d1_asian":58,"geo_population_d1_black":7796,"geo_population_d1_hispanic":351,"geo_population_d1_pi":0,"geo_population_d1_two":556,"geo_population_d1_white":10539,"geo_population_d1_unk":0,"geo_population_d2_male":10737,"geo_population_d2_female":8715,"geo_medincome":64709,"geo_households":4313,"geo_pctba":0.1613,"metric190_d1_native":0,"metric190_d1_asian":0,"metric190_d1_black":0.57,"metric190_d1_hispanic":0.02,"metric190_d1_pi":0,"metric190_d1_two":0.02,"metric190_d1_white":0.39,"metric190_d1_unk":0,"metric50_d7_less_than_10k":0.01,"metric50_d7_10k_to_15k":0.026,"metric50_d7_15k_to_25k":0.084,"metric50_d7_25k_to_35k":0.099,"metric50_d7_35k_to_50k":0.189,"metric50_d7_50k_to_65k":0.208,"metric50_d7_65k_to_75k":0.078,"metric50_d7_75k_to_100k":0.11,"metric50_d7_more_than_100k":0.195},{"geoid":"22039","geo_population":32335,"geo_population_d1_native":74,"geo_population_d1_asian":85,"geo_population_d1_black":8121,"geo_population_d1_hispanic":1352,"geo_population_d1_pi":20,"geo_population_d1_two":1131,"geo_population_d1_white":20969,"geo_population_d1_unk":583,"geo_population_d2_male":16410,"geo_population_d2_female":15925,"geo_medincome":34526,"geo_households":7679,"geo_pctba":0.1223,"metric190_d1_native":0,"metric190_d1_asian":0,"metric190_d1_black":0.38,"metric190_d1_hispanic":0.02,"metric190_d1_pi":0,"metric190_d1_two":0.04,"metric190_d1_white":0.56,"metric190_d1_unk":0,"metric50_d7_less_than_10k":0.041,"metric50_d7_10k_to_15k":0.056,"metric50_d7_15k_to_25k":0.156,"metric50_d7_25k_to_35k":0.179,"metric50_d7_35k_to_50k":0.187,"metric50_d7_50k_to_65k":0.144,"metric50_d7_65k_to_75k":0.056,"metric50_d7_75k_to_100k":0.1,"metric50_d7_more_than_100k":0.081},{"geoid":"22041","geo_population":19752,"geo_population_d1_native":9,"geo_population_d1_asian":44,"geo_population_d1_black":6007,"geo_population_d1_hispanic":328,"geo_population_d1_pi":4,"geo_population_d1_two":420,"geo_population_d1_white":12940,"geo_population_d1_unk":0,"geo_population_d2_male":9408,"geo_population_d2_female":10344,"geo_medincome":41129,"geo_households":5111,"geo_pctba":0.1535,"metric190_d1_native":0,"metric190_d1_asian":0,"metric190_d1_black":0.5,"metric190_d1_hispanic":0.01,"metric190_d1_pi":0,"metric190_d1_two":0.02,"metric190_d1_white":0.46,"metric190_d1_unk":0,"metric50_d7_less_than_10k":0.022,"metric50_d7_10k_to_15k":0.083,"metric50_d7_15k_to_25k":0.162,"metric50_d7_25k_to_35k":0.153,"metric50_d7_35k_to_50k":0.187,"metric50_d7_50k_to_65k":0.157,"metric50_d7_65k_to_75k":0.071,"metric50_d7_75k_to_100k":0.063,"metric50_d7_more_than_100k":0.103},{"geoid":"22043","geo_population":22185,"geo_population_d1_native":205,"geo_population_d1_asian":75,"geo_population_d1_black":3281,"geo_population_d1_hispanic":1190,"geo_population_d1_pi":0,"geo_population_d1_two":718,"geo_population_d1_white":16677,"geo_population_d1_unk":39,"geo_population_d2_male":12556,"geo_population_d2_female":9629,"geo_medincome":57362,"geo_households":4582,"geo_pctba":0.1203,"metric190_d1_native":0.01,"metric190_d1_asian":0,"metric190_d1_black":0.11,"metric190_d1_hispanic":0.01,"metric190_d1_pi":0,"metric190_d1_two":0.03,"metric190_d1_white":0.84,"metric190_d1_unk":0,"metric50_d7_less_than_10k":0.021,"metric50_d7_10k_to_15k":0.021,"metric50_d7_15k_to_25k":0.125,"metric50_d7_25k_to_35k":0.189,"metric50_d7_35k_to_50k":0.198,"metric50_d7_50k_to_65k":0.12,"metric50_d7_65k_to_75k":0.059,"metric50_d7_75k_to_100k":0.094,"metric50_d7_more_than_100k":0.174},{"geoid":"22045","geo_population":69958,"geo_population_d1_native":76,"geo_population_d1_asian":1858,"geo_population_d1_black":21683,"geo_population_d1_hispanic":3095,"geo_population_d1_pi":0,"geo_population_d1_two":2711,"geo_population_d1_white":40147,"geo_population_d1_unk":388,"geo_population_d2_male":34540,"geo_population_d2_female":35418,"geo_medincome":55190,"geo_households":18992,"geo_pctba":0.1416,"metric190_d1_native":0,"metric190_d1_asian":0.03,"metric190_d1_black":0.45,"metric190_d1_hispanic":0.06,"metric190_d1_pi":0,"metric190_d1_two":0.05,"metric190_d1_white":0.41,"metric190_d1_unk":0,"metric50_d7_less_than_10k":0.009,"metric50_d7_10k_to_15k":0.054,"metric50_d7_15k_to_25k":0.14,"metric50_d7_25k_to_35k":0.137,"metric50_d7_35k_to_50k":0.191,"metric50_d7_50k_to_65k":0.148,"metric50_d7_65k_to_75k":0.076,"metric50_d7_75k_to_100k":0.128,"metric50_d7_more_than_100k":0.117},{"geoid":"22047","geo_population":30210,"geo_population_d1_native":19,"geo_population_d1_asian":11,"geo_population_d1_black":13694,"geo_population_d1_hispanic":964,"geo_population_d1_pi":29,"geo_population_d1_two":1034,"geo_population_d1_white":14270,"geo_population_d1_unk":189,"geo_population_d2_male":15365,"geo_population_d2_female":14845,"geo_medincome":59410,"geo_households":7492,"geo_pctba":0.1493,"metric190_d1_native":0,"metric190_d1_asian":0.01,"metric190_d1_black":0.61,"metric190_d1_hispanic":0.03,"metric190_d1_pi":0,"metric190_d1_two":0.02,"metric190_d1_white":0.32,"metric190_d1_unk":0,"metric50_d7_less_than_10k":0.022,"metric50_d7_10k_to_15k":0.049,"metric50_d7_15k_to_25k":0.097,"metric50_d7_25k_to_35k":0.14,"metric50_d7_35k_to_50k":0.223,"metric50_d7_50k_to_65k":0.143,"metric50_d7_65k_to_75k":0.055,"metric50_d7_75k_to_100k":0.131,"metric50_d7_more_than_100k":0.139},{"geoid":"22049","geo_population":15093,"geo_population_d1_native":67,"geo_population_d1_asian":14,"geo_population_d1_black":3877,"geo_population_d1_hispanic":297,"geo_population_d1_pi":12,"geo_population_d1_two":486,"geo_population_d1_white":10158,"geo_population_d1_unk":182,"geo_population_d2_male":7624,"geo_population_d2_female":7469,"geo_medincome":40406,"geo_households":3591,"geo_pctba":0.1283,"metric190_d1_native":0,"metric190_d1_asian":0,"metric190_d1_black":0.3,"metric190_d1_hispanic":0.02,"metric190_d1_pi":0,"metric190_d1_two":0.03,"metric190_d1_white":0.63,"metric190_d1_unk":0,"metric50_d7_less_than_10k":0.026,"metric50_d7_10k_to_15k":0.051,"metric50_d7_15k_to_25k":0.206,"metric50_d7_25k_to_35k":0.122,"metric50_d7_35k_to_50k":0.167,"metric50_d7_50k_to_65k":0.119,"metric50_d7_65k_to_75k":0.083,"metric50_d7_75k_to_100k":0.113,"metric50_d7_more_than_100k":0.112},{"geoid":"22051","geo_population":436171,"geo_population_d1_native":767,"geo_population_d1_asian":17966,"geo_population_d1_black":115266,"geo_population_d1_hispanic":66079,"geo_population_d1_pi":87,"geo_population_d1_two":12422,"geo_population_d1_white":221346,"geo_population_d1_unk":2238,"geo_population_d2_male":212244,"geo_population_d2_female":223927,"geo_medincome":63257,"geo_households":108445,"geo_pctba":0.2978,"metric190_d1_native":0,"metric190_d1_asian":0.04,"metric190_d1_black":0.34,"metric190_d1_hispanic":0.37,"metric190_d1_pi":0,"metric190_d1_two":0.03,"metric190_d1_white":0.21,"metric190_d1_unk":0,"metric50_d7_less_than_10k":0.021,"metric50_d7_10k_to_15k":0.027,"metric50_d7_15k_to_25k":0.106,"metric50_d7_25k_to_35k":0.145,"metric50_d7_35k_to_50k":0.187,"metric50_d7_50k_to_65k":0.161,"metric50_d7_65k_to_75k":0.078,"metric50_d7_75k_to_100k":0.127,"metric50_d7_more_than_100k":0.147},{"geoid":"22053","geo_population":32277,"geo_population_d1_native":107,"geo_population_d1_asian":2,"geo_population_d1_black":5388,"geo_population_d1_hispanic":837,"geo_population_d1_pi":0,"geo_population_d1_two":1053,"geo_population_d1_white":24864,"geo_population_d1_unk":26,"geo_population_d2_male":16068,"geo_population_d2_female":16209,"geo_medincome":52470,"geo_households":8088,"geo_pctba":0.152,"metric190_d1_native":0.01,"metric190_d1_asian":0,"metric190_d1_black":0.19,"metric190_d1_hispanic":0.04,"metric190_d1_pi":0,"metric190_d1_two":0.08,"metric190_d1_white":0.68,"metric190_d1_unk":0,"metric50_d7_less_than_10k":0.027,"metric50_d7_10k_to_15k":0.047,"metric50_d7_15k_to_25k":0.098,"metric50_d7_25k_to_35k":0.188,"metric50_d7_35k_to_50k":0.193,"metric50_d7_50k_to_65k":0.107,"metric50_d7_65k_to_75k":0.069,"metric50_d7_75k_to_100k":0.105,"metric50_d7_more_than_100k":0.166},{"geoid":"22055","geo_population":243175,"geo_population_d1_native":253,"geo_population_d1_asian":4478,"geo_population_d1_black":62336,"geo_population_d1_hispanic":11370,"geo_population_d1_pi":118,"geo_population_d1_two":7487,"geo_population_d1_white":156204,"geo_population_d1_unk":929,"geo_population_d2_male":119067,"geo_population_d2_female":124108,"geo_medincome":66617,"geo_households":61584,"geo_pctba":0.3464,"metric190_d1_native":0,"metric190_d1_asian":0.02,"metric190_d1_black":0.4,"metric190_d1_hispanic":0.1,"metric190_d1_pi":0,"metric190_d1_two":0.03,"metric190_d1_white":0.44,"metric190_d1_unk":0,"metric50_d7_less_than_10k":0.021,"metric50_d7_10k_to_15k":0.03,"metric50_d7_15k_to_25k":0.086,"metric50_d7_25k_to_35k":0.135,"metric50_d7_35k_to_50k":0.176,"metric50_d7_50k_to_65k":0.17,"metric50_d7_65k_to_75k":0.068,"metric50_d7_75k_to_100k":0.12,"metric50_d7_more_than_100k":0.194},{"geoid":"22057","geo_population":97220,"geo_population_d1_native":1868,"geo_population_d1_asian":604,"geo_population_d1_black":12823,"geo_population_d1_hispanic":4372,"geo_population_d1_pi":2,"geo_population_d1_two":3421,"geo_population_d1_white":73964,"geo_population_d1_unk":166,"geo_population_d2_male":47908,"geo_population_d2_female":49312,"geo_medincome":61381,"geo_households":24826,"geo_pctba":0.1862,"metric190_d1_native":0.03,"metric190_d1_asian":0.01,"metric190_d1_black":0.19,"metric190_d1_hispanic":0.1,"metric190_d1_pi":0,"metric190_d1_two":0.07,"metric190_d1_white":0.6,"metric190_d1_unk":0,"metric50_d7_less_than_10k":0.013,"metric50_d7_10k_to_15k":0.028,"metric50_d7_15k_to_25k":0.092,"metric50_d7_25k_to_35k":0.153,"metric50_d7_35k_to_50k":0.189,"metric50_d7_50k_to_65k":0.155,"metric50_d7_65k_to_75k":0.089,"metric50_d7_75k_to_100k":0.121,"metric50_d7_more_than_100k":0.16},{"geoid":"22059","geo_population":14764,"geo_population_d1_native":58,"geo_population_d1_asian":278,"geo_population_d1_black":1732,"geo_population_d1_hispanic":582,"geo_population_d1_pi":78,"geo_population_d1_two":259,"geo_population_d1_white":11777,"geo_population_d1_unk":0,"geo_population_d2_male":7999,"geo_population_d2_female":6765,"geo_medincome":59926,"geo_households":3540,"geo_pctba":0.177,"metric190_d1_native":0.02,"metric190_d1_asian":0,"metric190_d1_black":0.09,"metric190_d1_hispanic":0.01,"metric190_d1_pi":0,"metric190_d1_two":0.03,"metric190_d1_white":0.86,"metric190_d1_unk":0,"metric50_d7_less_than_10k":0.002,"metric50_d7_10k_to_15k":0.052,"metric50_d7_15k_to_25k":0.101,"metric50_d7_25k_to_35k":0.141,"metric50_d7_35k_to_50k":0.16,"metric50_d7_50k_to_65k":0.169,"metric50_d7_65k_to_75k":0.058,"metric50_d7_75k_to_100k":0.202,"metric50_d7_more_than_100k":0.115},{"geoid":"22061","geo_population":48323,"geo_population_d1_native":231,"geo_population_d1_asian":670,"geo_population_d1_black":18055,"geo_population_d1_hispanic":1550,"geo_population_d1_pi":32,"geo_population_d1_two":1782,"geo_population_d1_white":25668,"geo_population_d1_unk":335,"geo_population_d2_male":23783,"geo_population_d2_female":24540,"geo_medincome":37001,"geo_households":9914,"geo_pctba":0.3657,"metric190_d1_native":0,"metric190_d1_asian":0.01,"metric190_d1_black":0.46,"metric190_d1_hispanic":0.07,"metric190_d1_pi":0,"metric190_d1_two":0.02,"metric190_d1_white":0.44,"metric190_d1_unk":0,"metric50_d7_less_than_10k":0.028,"metric50_d7_10k_to_15k":0.031,"metric50_d7_15k_to_25k":0.208,"metric50_d7_25k_to_35k":0.169,"metric50_d7_35k_to_50k":0.156,"metric50_d7_50k_to_65k":0.128,"metric50_d7_65k_to_75k":0.074,"metric50_d7_75k_to_100k":0.1,"metric50_d7_more_than_100k":0.105},{"geoid":"22063","geo_population":143425,"geo_population_d1_native":133,"geo_population_d1_asian":1168,"geo_population_d1_black":10684,"geo_population_d1_hispanic":6367,"geo_population_d1_pi":1,"geo_population_d1_two":3423,"geo_population_d1_white":121384,"geo_population_d1_unk":265,"geo_population_d2_male":70817,"geo_population_d2_female":72608,"geo_medincome":77978,"geo_households":35860,"geo_pctba":0.2174,"metric190_d1_native":0,"metric190_d1_asian":0.01,"metric190_d1_black":0.13,"metric190_d1_hispanic":0.12,"metric190_d1_pi":0,"metric190_d1_two":0.03,"metric190_d1_white":0.72,"metric190_d1_unk":0,"metric50_d7_less_than_10k":0.014,"metric50_d7_10k_to_15k":0.025,"metric50_d7_15k_to_25k":0.067,"metric50_d7_25k_to_35k":0.116,"metric50_d7_35k_to_50k":0.176,"metric50_d7_50k_to_65k":0.177,"metric50_d7_65k_to_75k":0.073,"metric50_d7_75k_to_100k":0.162,"metric50_d7_more_than_100k":0.189},{"geoid":"22065","geo_population":10028,"geo_population_d1_native":17,"geo_population_d1_asian":0,"geo_population_d1_black":6243,"geo_population_d1_hispanic":294,"geo_population_d1_pi":0,"geo_population_d1_two":97,"geo_population_d1_white":3377,"geo_population_d1_unk":0,"geo_population_d2_male":4770,"geo_population_d2_female":5258,"geo_medincome":34508,"geo_households":2034,"geo_pctba":0.1402,"metric190_d1_native":0,"metric190_d1_asian":0,"metric190_d1_black":0.94,"metric190_d1_hispanic":0.01,"metric190_d1_pi":0,"metric190_d1_two":0.02,"metric190_d1_white":0.03,"metric190_d1_unk":0,"metric50_d7_less_than_10k":0.04,"metric50_d7_10k_to_15k":0.087,"metric50_d7_15k_to_25k":0.184,"metric50_d7_25k_to_35k":0.161,"metric50_d7_35k_to_50k":0.15,"metric50_d7_50k_to_65k":0.155,"metric50_d7_65k_to_75k":0.085,"metric50_d7_75k_to_100k":0.07,"metric50_d7_more_than_100k":0.068},{"geoid":"22067","geo_population":25438,"geo_population_d1_native":13,"geo_population_d1_asian":131,"geo_population_d1_black":12269,"geo_population_d1_hispanic":392,"geo_population_d1_pi":38,"geo_population_d1_two":312,"geo_population_d1_white":12196,"geo_population_d1_unk":87,"geo_population_d2_male":12407,"geo_population_d2_female":13031,"geo_medincome":37875,"geo_households":5752,"geo_pctba":0.1287,"metric190_d1_native":0,"metric190_d1_asian":0.01,"metric190_d1_black":0.64,"metric190_d1_hispanic":0.01,"metric190_d1_pi":0,"metric190_d1_two":0.02,"metric190_d1_white":0.32,"metric190_d1_unk":0,"metric50_d7_less_than_10k":0.023,"metric50_d7_10k_to_15k":0.053,"metric50_d7_15k_to_25k":0.212,"metric50_d7_25k_to_35k":0.187,"metric50_d7_35k_to_50k":0.181,"metric50_d7_50k_to_65k":0.145,"metric50_d7_65k_to_75k":0.056,"metric50_d7_75k_to_100k":0.056,"metric50_d7_more_than_100k":0.087},{"geoid":"22069","geo_population":37478,"geo_population_d1_native":273,"geo_population_d1_asian":237,"geo_population_d1_black":15117,"geo_population_d1_hispanic":948,"geo_population_d1_pi":0,"geo_population_d1_two":1180,"geo_population_d1_white":19084,"geo_population_d1_unk":639,"geo_population_d2_male":18089,"geo_population_d2_female":19389,"geo_medincome":41310,"geo_households":7859,"geo_pctba":0.2283,"metric190_d1_native":0.01,"metric190_d1_asian":0.01,"metric190_d1_black":0.54,"metric190_d1_hispanic":0.04,"metric190_d1_pi":0,"metric190_d1_two":0.03,"metric190_d1_white":0.38,"metric190_d1_unk":0,"metric50_d7_less_than_10k":0.042,"metric50_d7_10k_to_15k":0.042,"metric50_d7_15k_to_25k":0.135,"metric50_d7_25k_to_35k":0.167,"metric50_d7_35k_to_50k":0.162,"metric50_d7_50k_to_65k":0.138,"metric50_d7_65k_to_75k":0.091,"metric50_d7_75k_to_100k":0.113,"metric50_d7_more_than_100k":0.111},{"geoid":"22071","geo_population":380408,"geo_population_d1_native":404,"geo_population_d1_asian":10646,"geo_population_d1_black":215595,"geo_population_d1_hispanic":21528,"geo_population_d1_pi":61,"geo_population_d1_two":11835,"geo_population_d1_white":117202,"geo_population_d1_unk":3137,"geo_population_d2_male":179688,"geo_population_d2_female":200720,"geo_medincome":51116,"geo_households":72544,"geo_pctba":0.4074,"metric190_d1_native":0,"metric190_d1_asian":0.02,"metric190_d1_black":0.72,"metric190_d1_hispanic":0.14,"metric190_d1_pi":0,"metric190_d1_two":0.02,"metric190_d1_white":0.1,"metric190_d1_unk":0,"metric50_d7_less_than_10k":0.02,"metric50_d7_10k_to_15k":0.036,"metric50_d7_15k_to_25k":0.099,"metric50_d7_25k_to_35k":0.136,"metric50_d7_35k_to_50k":0.176,"metric50_d7_50k_to_65k":0.158,"metric50_d7_65k_to_75k":0.072,"metric50_d7_75k_to_100k":0.109,"metric50_d7_more_than_100k":0.194},{"geoid":"22073","geo_population":159585,"geo_population_d1_native":174,"geo_population_d1_asian":1786,"geo_population_d1_black":59433,"geo_population_d1_hispanic":3709,"geo_population_d1_pi":19,"geo_population_d1_two":3197,"geo_population_d1_white":90693,"geo_population_d1_unk":574,"geo_population_d2_male":77016,"geo_population_d2_female":82569,"geo_medincome":49261,"geo_households":37742,"geo_pctba":0.2582,"metric190_d1_native":0,"metric190_d1_asian":0.01,"metric190_d1_black":0.5,"metric190_d1_hispanic":0.04,"metric190_d1_pi":0,"metric190_d1_two":0.02,"metric190_d1_white":0.43,"metric190_d1_unk":0,"metric50_d7_less_than_10k":0.022,"metric50_d7_10k_to_15k":0.036,"metric50_d7_15k_to_25k":0.116,"metric50_d7_25k_to_35k":0.145,"metric50_d7_35k_to_50k":0.212,"metric50_d7_50k_to_65k":0.147,"metric50_d7_65k_to_75k":0.084,"metric50_d7_75k_to_100k":0.1,"metric50_d7_more_than_100k":0.139},{"geoid":"22075","geo_population":23305,"geo_population_d1_native":225,"geo_population_d1_asian":996,"geo_population_d1_black":4577,"geo_population_d1_hispanic":1885,"geo_population_d1_pi":23,"geo_population_d1_two":1162,"geo_population_d1_white":14388,"geo_population_d1_unk":49,"geo_population_d2_male":12112,"geo_population_d2_female":11193,"geo_medincome":77996,"geo_households":6224,"geo_pctba":0.19,"metric190_d1_native":0.01,"metric190_d1_asian":0.04,"metric190_d1_black":0.25,"metric190_d1_hispanic":0.13,"metric190_d1_pi":0,"metric190_d1_two":0.07,"metric190_d1_white":0.49,"metric190_d1_unk":0,"metric50_d7_less_than_10k":0.019,"metric50_d7_10k_to_15k":0.041,"metric50_d7_15k_to_25k":0.121,"metric50_d7_25k_to_35k":0.119,"metric50_d7_35k_to_50k":0.178,"metric50_d7_50k_to_65k":0.125,"metric50_d7_65k_to_75k":0.103,"metric50_d7_75k_to_100k":0.128,"metric50_d7_more_than_100k":0.166},{"geoid":"22077","geo_population":20652,"geo_population_d1_native":40,"geo_population_d1_asian":63,"geo_population_d1_black":6984,"geo_population_d1_hispanic":649,"geo_population_d1_pi":0,"geo_population_d1_two":533,"geo_population_d1_white":12360,"geo_population_d1_unk":23,"geo_population_d2_male":10201,"geo_population_d2_female":10451,"geo_medincome":53045,"geo_households":4987,"geo_pctba":0.1477,"metric190_d1_native":0,"metric190_d1_asian":0,"metric190_d1_black":0.54,"metric190_d1_hispanic":0.06,"metric190_d1_pi":0,"metric190_d1_two":0.01,"metric190_d1_white":0.38,"metric190_d1_unk":0,"metric50_d7_less_than_10k":0.018,"metric50_d7_10k_to_15k":0.034,"metric50_d7_15k_to_25k":0.079,"metric50_d7_25k_to_35k":0.154,"metric50_d7_35k_to_50k":0.2,"metric50_d7_50k_to_65k":0.181,"metric50_d7_65k_to_75k":0.06,"metric50_d7_75k_to_100k":0.143,"metric50_d7_more_than_100k":0.131},{"geoid":"22079","geo_population":129536,"geo_population_d1_native":488,"geo_population_d1_asian":1523,"geo_population_d1_black":40238,"geo_population_d1_hispanic":4572,"geo_population_d1_pi":15,"geo_population_d1_two":4086,"geo_population_d1_white":78322,"geo_population_d1_unk":292,"geo_population_d2_male":62847,"geo_population_d2_female":66689,"geo_medincome":55407,"geo_households":31710,"geo_pctba":0.223,"metric190_d1_native":0.01,"metric190_d1_asian":0.01,"metric190_d1_black":0.41,"metric190_d1_hispanic":0.05,"metric190_d1_pi":0,"metric190_d1_two":0.03,"metric190_d1_white":0.49,"metric190_d1_unk":0,"metric50_d7_less_than_10k":0.02,"metric50_d7_10k_to_15k":0.031,"metric50_d7_15k_to_25k":0.13,"metric50_d7_25k_to_35k":0.169,"metric50_d7_35k_to_50k":0.187,"metric50_d7_50k_to_65k":0.151,"metric50_d7_65k_to_75k":0.072,"metric50_d7_75k_to_100k":0.11,"metric50_d7_more_than_100k":0.131},{"geoid":"22081","geo_population":7631,"geo_population_d1_native":0,"geo_population_d1_asian":0,"geo_population_d1_black":2979,"geo_population_d1_hispanic":168,"geo_population_d1_pi":0,"geo_population_d1_two":222,"geo_population_d1_white":4249,"geo_population_d1_unk":13,"geo_population_d2_male":3839,"geo_population_d2_female":3792,"geo_medincome":43821,"geo_households":1917,"geo_pctba":0.1064,"metric190_d1_native":0,"metric190_d1_asian":0.01,"metric190_d1_black":0.61,"metric190_d1_hispanic":0.02,"metric190_d1_pi":0,"metric190_d1_two":0.04,"metric190_d1_white":0.32,"metric190_d1_unk":0,"metric50_d7_less_than_10k":0.037,"metric50_d7_10k_to_15k":0.067,"metric50_d7_15k_to_25k":0.124,"metric50_d7_25k_to_35k":0.165,"metric50_d7_35k_to_50k":0.152,"metric50_d7_50k_to_65k":0.206,"metric50_d7_65k_to_75k":0.016,"metric50_d7_75k_to_100k":0.114,"metric50_d7_more_than_100k":0.119},{"geoid":"22083","geo_population":20028,"geo_population_d1_native":21,"geo_population_d1_asian":0,"geo_population_d1_black":7127,"geo_population_d1_hispanic":473,"geo_population_d1_pi":0,"geo_population_d1_two":270,"geo_population_d1_white":12137,"geo_population_d1_unk":0,"geo_population_d2_male":9951,"geo_population_d2_female":10077,"geo_medincome":48125,"geo_households":5085,"geo_pctba":0.1633,"metric190_d1_native":0,"metric190_d1_asian":0,"metric190_d1_black":0.52,"metric190_d1_hispanic":0.02,"metric190_d1_pi":0,"metric190_d1_two":0.02,"metric190_d1_white":0.44,"metric190_d1_unk":0,"metric50_d7_less_than_10k":0.009,"metric50_d7_10k_to_15k":0.016,"metric50_d7_15k_to_25k":0.207,"metric50_d7_25k_to_35k":0.124,"metric50_d7_35k_to_50k":0.187,"metric50_d7_50k_to_65k":0.157,"metric50_d7_65k_to_75k":0.078,"metric50_d7_75k_to_100k":0.102,"metric50_d7_more_than_100k":0.122},{"geoid":"22085","geo_population":22209,"geo_population_d1_native":1238,"geo_population_d1_asian":77,"geo_population_d1_black":3200,"geo_population_d1_hispanic":961,"geo_population_d1_pi":0,"geo_population_d1_two":1900,"geo_population_d1_white":14695,"geo_population_d1_unk":138,"geo_population_d2_male":11048,"geo_population_d2_female":11161,"geo_medincome":40777,"geo_households":5292,"geo_pctba":0.1331,"metric190_d1_native":0.16,"metric190_d1_asian":0,"metric190_d1_black":0.21,"metric190_d1_hispanic":0.03,"metric190_d1_pi":0,"metric190_d1_two":0.08,"metric190_d1_white":0.51,"metric190_d1_unk":0,"metric50_d7_less_than_10k":0.045,"metric50_d7_10k_to_15k":0.023,"metric50_d7_15k_to_25k":0.123,"metric50_d7_25k_to_35k":0.2,"metric50_d7_35k_to_50k":0.183,"metric50_d7_50k_to_65k":0.167,"metric50_d7_65k_to_75k":0.064,"metric50_d7_75k_to_100k":0.092,"metric50_d7_more_than_100k":0.102},{"geoid":"22087","geo_population":44038,"geo_population_d1_native":312,"geo_population_d1_asian":1076,"geo_population_d1_black":10385,"geo_population_d1_hispanic":4667,"geo_population_d1_pi":0,"geo_population_d1_two":1251,"geo_population_d1_white":26325,"geo_population_d1_unk":22,"geo_population_d2_male":21711,"geo_population_d2_female":22327,"geo_medincome":55857,"geo_households":10421,"geo_pctba":0.1682,"metric190_d1_native":0,"metric190_d1_asian":0.02,"metric190_d1_black":0.31,"metric190_d1_hispanic":0.18,"metric190_d1_pi":0,"metric190_d1_two":0.04,"metric190_d1_white":0.44,"metric190_d1_unk":0,"metric50_d7_less_than_10k":0.01,"metric50_d7_10k_to_15k":0.031,"metric50_d7_15k_to_25k":0.108,"metric50_d7_25k_to_35k":0.138,"metric50_d7_35k_to_50k":0.213,"metric50_d7_50k_to_65k":0.169,"metric50_d7_65k_to_75k":0.083,"metric50_d7_75k_to_100k":0.14,"metric50_d7_more_than_100k":0.108},{"geoid":"22089","geo_population":52191,"geo_population_d1_native":525,"geo_population_d1_asian":492,"geo_population_d1_black":12160,"geo_population_d1_hispanic":3426,"geo_population_d1_pi":3,"geo_population_d1_two":1704,"geo_population_d1_white":33536,"geo_population_d1_unk":345,"geo_population_d2_male":26017,"geo_population_d2_female":26174,"geo_medincome":79191,"geo_households":13859,"geo_pctba":0.2716,"metric190_d1_native":0,"metric190_d1_asian":0.01,"metric190_d1_black":0.32,"metric190_d1_hispanic":0.11,"metric190_d1_pi":0,"metric190_d1_two":0.04,"metric190_d1_white":0.51,"metric190_d1_unk":0,"metric50_d7_less_than_10k":0.012,"metric50_d7_10k_to_15k":0.026,"metric50_d7_15k_to_25k":0.071,"metric50_d7_25k_to_35k":0.128,"metric50_d7_35k_to_50k":0.201,"metric50_d7_50k_to_65k":0.16,"metric50_d7_65k_to_75k":0.094,"metric50_d7_75k_to_100k":0.132,"metric50_d7_more_than_100k":0.176},{"geoid":"22091","geo_population":10872,"geo_population_d1_native":0,"geo_population_d1_asian":15,"geo_population_d1_black":5627,"geo_population_d1_hispanic":220,"geo_population_d1_pi":0,"geo_population_d1_two":172,"geo_population_d1_white":4838,"geo_population_d1_unk":0,"geo_population_d2_male":5400,"geo_population_d2_female":5472,"geo_medincome":46402,"geo_households":2412,"geo_pctba":0.1201,"metric190_d1_native":0,"metric190_d1_asian":0,"metric190_d1_black":0.9,"metric190_d1_hispanic":0.03,"metric190_d1_pi":0,"metric190_d1_two":0.02,"metric190_d1_white":0.05,"metric190_d1_unk":0,"metric50_d7_less_than_10k":0.082,"metric50_d7_10k_to_15k":0.055,"metric50_d7_15k_to_25k":0.084,"metric50_d7_25k_to_35k":0.207,"metric50_d7_35k_to_50k":0.176,"metric50_d7_50k_to_65k":0.098,"metric50_d7_65k_to_75k":0.072,"metric50_d7_75k_to_100k":0.133,"metric50_d7_more_than_100k":0.092},{"geoid":"22093","geo_population":20090,"geo_population_d1_native":0,"geo_population_d1_asian":5,"geo_population_d1_black":9732,"geo_population_d1_hispanic":371,"geo_population_d1_pi":0,"geo_population_d1_two":129,"geo_population_d1_white":9853,"geo_population_d1_unk":0,"geo_population_d2_male":9716,"geo_population_d2_female":10374,"geo_medincome":62946,"geo_households":5562,"geo_pctba":0.1867,"metric190_d1_native":0,"metric190_d1_asian":0,"metric190_d1_black":0.59,"metric190_d1_hispanic":0.02,"metric190_d1_pi":0,"metric190_d1_two":0.01,"metric190_d1_white":0.38,"metric190_d1_unk":0,"metric50_d7_less_than_10k":0.008,"metric50_d7_10k_to_15k":0.029,"metric50_d7_15k_to_25k":0.151,"metric50_d7_25k_to_35k":0.137,"metric50_d7_35k_to_50k":0.149,"metric50_d7_50k_to_65k":0.14,"metric50_d7_65k_to_75k":0.067,"metric50_d7_75k_to_100k":0.122,"metric50_d7_more_than_100k":0.197},{"geoid":"22095","geo_population":41986,"geo_population_d1_native":68,"geo_population_d1_asian":379,"geo_population_d1_black":23434,"geo_population_d1_hispanic":3061,"geo_population_d1_pi":1,"geo_population_d1_two":1491,"geo_population_d1_white":12916,"geo_population_d1_unk":636,"geo_population_d2_male":20563,"geo_population_d2_female":21423,"geo_medincome":65114,"geo_households":10775,"geo_pctba":0.1638,"metric190_d1_native":0,"metric190_d1_asian":0,"metric190_d1_black":0.71,"metric190_d1_hispanic":0.16,"metric190_d1_pi":0,"metric190_d1_two":0.02,"metric190_d1_white":0.1,"metric190_d1_unk":0,"metric50_d7_less_than_10k":0.019,"metric50_d7_10k_to_15k":0.049,"metric50_d7_15k_to_25k":0.119,"metric50_d7_25k_to_35k":0.139,"metric50_d7_35k_to_50k":0.172,"metric50_d7_50k_to_65k":0.152,"metric50_d7_65k_to_75k":0.088,"metric50_d7_75k_to_100k":0.142,"metric50_d7_more_than_100k":0.119},{"geoid":"22097","geo_population":82574,"geo_population_d1_native":81,"geo_population_d1_asian":459,"geo_population_d1_black":33350,"geo_population_d1_hispanic":2056,"geo_population_d1_pi":176,"geo_population_d1_two":2039,"geo_population_d1_white":44269,"geo_population_d1_unk":144,"geo_population_d2_male":40045,"geo_population_d2_female":42529,"geo_medincome":44478,"geo_households":20835,"geo_pctba":0.1412,"metric190_d1_native":0,"metric190_d1_asian":0.01,"metric190_d1_black":0.58,"metric190_d1_hispanic":0.04,"metric190_d1_pi":0,"metric190_d1_two":0.02,"metric190_d1_white":0.35,"metric190_d1_unk":0,"metric50_d7_less_than_10k":0.022,"metric50_d7_10k_to_15k":0.032,"metric50_d7_15k_to_25k":0.152,"metric50_d7_25k_to_35k":0.158,"metric50_d7_35k_to_50k":0.218,"metric50_d7_50k_to_65k":0.141,"metric50_d7_65k_to_75k":0.071,"metric50_d7_75k_to_100k":0.098,"metric50_d7_more_than_100k":0.108},{"geoid":"22099","geo_population":51856,"geo_population_d1_native":110,"geo_population_d1_asian":493,"geo_population_d1_black":14903,"geo_population_d1_hispanic":1647,"geo_population_d1_pi":74,"geo_population_d1_two":1254,"geo_population_d1_white":33297,"geo_population_d1_unk":78,"geo_population_d2_male":25442,"geo_population_d2_female":26414,"geo_medincome":50806,"geo_households":12944,"geo_pctba":0.142,"metric190_d1_native":0,"metric190_d1_asian":0.01,"metric190_d1_black":0.45,"metric190_d1_hispanic":0.04,"metric190_d1_pi":0,"metric190_d1_two":0.04,"metric190_d1_white":0.46,"metric190_d1_unk":0,"metric50_d7_less_than_10k":0.016,"metric50_d7_10k_to_15k":0.026,"metric50_d7_15k_to_25k":0.102,"metric50_d7_25k_to_35k":0.185,"metric50_d7_35k_to_50k":0.215,"metric50_d7_50k_to_65k":0.15,"metric50_d7_65k_to_75k":0.081,"metric50_d7_75k_to_100k":0.131,"metric50_d7_more_than_100k":0.094},{"geoid":"22101","geo_population":49114,"geo_population_d1_native":738,"geo_population_d1_asian":625,"geo_population_d1_black":14534,"geo_population_d1_hispanic":3566,"geo_population_d1_pi":13,"geo_population_d1_two":2168,"geo_population_d1_white":27416,"geo_population_d1_unk":54,"geo_population_d2_male":24037,"geo_population_d2_female":25077,"geo_medincome":47322,"geo_households":12336,"geo_pctba":0.1232,"metric190_d1_native":0.02,"metric190_d1_asian":0.01,"metric190_d1_black":0.37,"metric190_d1_hispanic":0.15,"metric190_d1_pi":0,"metric190_d1_two":0.07,"metric190_d1_white":0.38,"metric190_d1_unk":0,"metric50_d7_less_than_10k":0.019,"metric50_d7_10k_to_15k":0.04,"metric50_d7_15k_to_25k":0.137,"metric50_d7_25k_to_35k":0.141,"metric50_d7_35k_to_50k":0.262,"metric50_d7_50k_to_65k":0.121,"metric50_d7_65k_to_75k":0.06,"metric50_d7_75k_to_100k":0.084,"metric50_d7_more_than_100k":0.137},{"geoid":"22103","geo_population":266168,"geo_population_d1_native":792,"geo_population_d1_asian":3667,"geo_population_d1_black":31846,"geo_population_d1_hispanic":16212,"geo_population_d1_pi":689,"geo_population_d1_two":9054,"geo_population_d1_white":201872,"geo_population_d1_unk":2036,"geo_population_d2_male":130486,"geo_population_d2_female":135682,"geo_medincome":76914,"geo_households":71263,"geo_pctba":0.3639,"metric190_d1_native":0,"metric190_d1_asian":0.01,"metric190_d1_black":0.21,"metric190_d1_hispanic":0.1,"metric190_d1_pi":0,"metric190_d1_two":0.04,"metric190_d1_white":0.63,"metric190_d1_unk":0,"metric50_d7_less_than_10k":0.018,"metric50_d7_10k_to_15k":0.026,"metric50_d7_15k_to_25k":0.077,"metric50_d7_25k_to_35k":0.12,"metric50_d7_35k_to_50k":0.163,"metric50_d7_50k_to_65k":0.157,"metric50_d7_65k_to_75k":0.077,"metric50_d7_75k_to_100k":0.141,"metric50_d7_more_than_100k":0.222},{"geoid":"22105","geo_population":133953,"geo_population_d1_native":100,"geo_population_d1_asian":954,"geo_population_d1_black":39602,"geo_population_d1_hispanic":6332,"geo_population_d1_pi":43,"geo_population_d1_two":3924,"geo_population_d1_white":82634,"geo_population_d1_unk":364,"geo_population_d2_male":65523,"geo_population_d2_female":68430,"geo_medincome":55274,"geo_households":32042,"geo_pctba":0.2149,"metric190_d1_native":0,"metric190_d1_asian":0.01,"metric190_d1_black":0.46,"metric190_d1_hispanic":0.09,"metric190_d1_pi":0,"metric190_d1_two":0.05,"metric190_d1_white":0.38,"metric190_d1_unk":0,"metric50_d7_less_than_10k":0.022,"metric50_d7_10k_to_15k":0.026,"metric50_d7_15k_to_25k":0.142,"metric50_d7_25k_to_35k":0.149,"metric50_d7_35k_to_50k":0.186,"metric50_d7_50k_to_65k":0.151,"metric50_d7_65k_to_75k":0.075,"metric50_d7_75k_to_100k":0.111,"metric50_d7_more_than_100k":0.138},{"geoid":"22107","geo_population":4127,"geo_population_d1_native":0,"geo_population_d1_asian":34,"geo_population_d1_black":2168,"geo_population_d1_hispanic":129,"geo_population_d1_pi":0,"geo_population_d1_two":87,"geo_population_d1_white":1709,"geo_population_d1_unk":0,"geo_population_d2_male":1948,"geo_population_d2_female":2179,"geo_medincome":35653,"geo_households":808,"geo_pctba":0.1422,"metric190_d1_native":0,"metric190_d1_asian":0,"metric190_d1_black":0.83,"metric190_d1_hispanic":0.01,"metric190_d1_pi":0,"metric190_d1_two":0.02,"metric190_d1_white":0.14,"metric190_d1_unk":0,"metric50_d7_less_than_10k":0.02,"metric50_d7_10k_to_15k":0.051,"metric50_d7_15k_to_25k":0.288,"metric50_d7_25k_to_35k":0.106,"metric50_d7_35k_to_50k":0.264,"metric50_d7_50k_to_65k":0.047,"metric50_d7_65k_to_75k":0.133,"metric50_d7_75k_to_100k":0.069,"metric50_d7_more_than_100k":0.023},{"geoid":"22109","geo_population":108862,"geo_population_d1_native":5696,"geo_population_d1_asian":1301,"geo_population_d1_black":20654,"geo_population_d1_hispanic":5818,"geo_population_d1_pi":24,"geo_population_d1_two":3756,"geo_population_d1_white":71509,"geo_population_d1_unk":104,"geo_population_d2_male":53934,"geo_population_d2_female":54928,"geo_medincome":63088,"geo_households":28412,"geo_pctba":0.1705,"metric190_d1_native":0.07,"metric190_d1_asian":0.01,"metric190_d1_black":0.24,"metric190_d1_hispanic":0.13,"metric190_d1_pi":0,"metric190_d1_two":0.1,"metric190_d1_white":0.46,"metric190_d1_unk":0,"metric50_d7_less_than_10k":0.029,"metric50_d7_10k_to_15k":0.03,"metric50_d7_15k_to_25k":0.096,"metric50_d7_25k_to_35k":0.149,"metric50_d7_35k_to_50k":0.166,"metric50_d7_50k_to_65k":0.154,"metric50_d7_65k_to_75k":0.089,"metric50_d7_75k_to_100k":0.12,"metric50_d7_more_than_100k":0.167},{"geoid":"22111","geo_population":21049,"geo_population_d1_native":29,"geo_population_d1_asian":6,"geo_population_d1_black":4976,"geo_population_d1_hispanic":1099,"geo_population_d1_pi":6,"geo_population_d1_two":326,"geo_population_d1_white":14607,"geo_population_d1_unk":0,"geo_population_d2_male":10450,"geo_population_d2_female":10599,"geo_medincome":47068,"geo_households":5330,"geo_pctba":0.1737,"metric190_d1_native":0,"metric190_d1_asian":0.01,"metric190_d1_black":0.28,"metric190_d1_hispanic":0.12,"metric190_d1_pi":0,"metric190_d1_two":0.02,"metric190_d1_white":0.56,"metric190_d1_unk":0,"metric50_d7_less_than_10k":0.012,"metric50_d7_10k_to_15k":0.02,"metric50_d7_15k_to_25k":0.136,"metric50_d7_25k_to_35k":0.177,"metric50_d7_35k_to_50k":0.208,"metric50_d7_50k_to_65k":0.121,"metric50_d7_65k_to_75k":0.09,"metric50_d7_75k_to_100k":0.106,"metric50_d7_more_than_100k":0.129},{"geoid":"22113","geo_population":57202,"geo_population_d1_native":89,"geo_population_d1_asian":1026,"geo_population_d1_black":7718,"geo_population_d1_hispanic":2174,"geo_population_d1_pi":127,"geo_population_d1_two":1777,"geo_population_d1_white":44210,"geo_population_d1_unk":81,"geo_population_d2_male":27840,"geo_population_d2_female":29362,"geo_medincome":56194,"geo_households":15579,"geo_pctba":0.1874,"metric190_d1_native":0,"metric190_d1_asian":0.02,"metric190_d1_black":0.19,"metric190_d1_hispanic":0.05,"metric190_d1_pi":0,"metric190_d1_two":0.05,"metric190_d1_white":0.69,"metric190_d1_unk":0,"metric50_d7_less_than_10k":0.016,"metric50_d7_10k_to_15k":0.04,"metric50_d7_15k_to_25k":0.133,"metric50_d7_25k_to_35k":0.141,"metric50_d7_35k_to_50k":0.143,"metric50_d7_50k_to_65k":0.19,"metric50_d7_65k_to_75k":0.074,"metric50_d7_75k_to_100k":0.123,"metric50_d7_more_than_100k":0.138},{"geoid":"22115","geo_population":48452,"geo_population_d1_native":452,"geo_population_d1_asian":783,"geo_population_d1_black":6414,"geo_population_d1_hispanic":4664,"geo_population_d1_pi":176,"geo_population_d1_two":2066,"geo_population_d1_white":33815,"geo_population_d1_unk":82,"geo_population_d2_male":25336,"geo_population_d2_female":23116,"geo_medincome":56547,"geo_households":12221,"geo_pctba":0.1873,"metric190_d1_native":0.01,"metric190_d1_asian":0.01,"metric190_d1_black":0.13,"metric190_d1_hispanic":0.1,"metric190_d1_pi":0.01,"metric190_d1_two":0.07,"metric190_d1_white":0.67,"metric190_d1_unk":0,"metric50_d7_less_than_10k":0.04,"metric50_d7_10k_to_15k":0.041,"metric50_d7_15k_to_25k":0.126,"metric50_d7_25k_to_35k":0.188,"metric50_d7_35k_to_50k":0.199,"metric50_d7_50k_to_65k":0.166,"metric50_d7_65k_to_75k":0.06,"metric50_d7_75k_to_100k":0.102,"metric50_d7_more_than_100k":0.078},{"geoid":"22117","geo_population":45514,"geo_population_d1_native":115,"geo_population_d1_asian":41,"geo_population_d1_black":13809,"geo_population_d1_hispanic":1202,"geo_population_d1_pi":0,"geo_population_d1_two":995,"geo_population_d1_white":29265,"geo_population_d1_unk":87,"geo_population_d2_male":22961,"geo_population_d2_female":22553,"geo_medincome":41803,"geo_households":11189,"geo_pctba":0.1172,"metric190_d1_native":0,"metric190_d1_asian":0,"metric190_d1_black":0.37,"metric190_d1_hispanic":0.04,"metric190_d1_pi":0,"metric190_d1_two":0.03,"metric190_d1_white":0.55,"metric190_d1_unk":0,"metric50_d7_less_than_10k":0.017,"metric50_d7_10k_to_15k":0.029,"metric50_d7_15k_to_25k":0.19,"metric50_d7_25k_to_35k":0.193,"metric50_d7_35k_to_50k":0.2,"metric50_d7_50k_to_65k":0.102,"metric50_d7_65k_to_75k":0.074,"metric50_d7_75k_to_100k":0.101,"metric50_d7_more_than_100k":0.093},{"geoid":"22119","geo_population":36761,"geo_population_d1_native":81,"geo_population_d1_asian":93,"geo_population_d1_black":12323,"geo_population_d1_hispanic":828,"geo_population_d1_pi":7,"geo_population_d1_two":698,"geo_population_d1_white":22711,"geo_population_d1_unk":20,"geo_population_d2_male":18033,"geo_population_d2_female":18728,"geo_medincome":34263,"geo_households":9505,"geo_pctba":0.1441,"metric190_d1_native":0,"metric190_d1_asian":0.01,"metric190_d1_black":0.41,"metric190_d1_hispanic":0.03,"metric190_d1_pi":0,"metric190_d1_two":0.03,"metric190_d1_white":0.51,"metric190_d1_unk":0,"metric50_d7_less_than_10k":0.032,"metric50_d7_10k_to_15k":0.074,"metric50_d7_15k_to_25k":0.277,"metric50_d7_25k_to_35k":0.162,"metric50_d7_35k_to_50k":0.135,"metric50_d7_50k_to_65k":0.119,"metric50_d7_65k_to_75k":0.048,"metric50_d7_75k_to_100k":0.083,"metric50_d7_more_than_100k":0.07},{"geoid":"22121","geo_population":27377,"geo_population_d1_native":0,"geo_population_d1_asian":129,"geo_population_d1_black":11214,"geo_population_d1_hispanic":919,"geo_population_d1_pi":0,"geo_population_d1_two":271,"geo_population_d1_white":14827,"geo_population_d1_unk":17,"geo_population_d2_male":13586,"geo_population_d2_female":13791,"geo_medincome":80510,"geo_households":7110,"geo_pctba":0.2308,"metric190_d1_native":0,"metric190_d1_asian":0,"metric190_d1_black":0.5,"metric190_d1_hispanic":0.07,"metric190_d1_pi":0,"metric190_d1_two":0.01,"metric190_d1_white":0.4,"metric190_d1_unk":0,"metric50_d7_less_than_10k":0.008,"metric50_d7_10k_to_15k":0.027,"metric50_d7_15k_to_25k":0.09,"metric50_d7_25k_to_35k":0.127,"metric50_d7_35k_to_50k":0.188,"metric50_d7_50k_to_65k":0.175,"metric50_d7_65k_to_75k":0.083,"metric50_d7_75k_to_100k":0.137,"metric50_d7_more_than_100k":0.164},{"geoid":"22123","geo_population":9800,"geo_population_d1_native":8,"geo_population_d1_asian":1,"geo_population_d1_black":1509,"geo_population_d1_hispanic":412,"geo_population_d1_pi":7,"geo_population_d1_two":50,"geo_population_d1_white":7781,"geo_population_d1_unk":32,"geo_population_d2_male":4829,"geo_population_d2_female":4971,"geo_medincome":45035,"geo_households":2472,"geo_pctba":0.1143,"metric190_d1_native":0,"metric190_d1_asian":0.01,"metric190_d1_black":0.17,"metric190_d1_hispanic":0.03,"metric190_d1_pi":0,"metric190_d1_two":0.02,"metric190_d1_white":0.76,"metric190_d1_unk":0,"metric50_d7_less_than_10k":0.039,"metric50_d7_10k_to_15k":0.026,"metric50_d7_15k_to_25k":0.143,"metric50_d7_25k_to_35k":0.148,"metric50_d7_35k_to_50k":0.24,"metric50_d7_50k_to_65k":0.157,"metric50_d7_65k_to_75k":0.084,"metric50_d7_75k_to_100k":0.04,"metric50_d7_more_than_100k":0.123},{"geoid":"22125","geo_population":15358,"geo_population_d1_native":92,"geo_population_d1_asian":0,"geo_population_d1_black":6794,"geo_population_d1_hispanic":225,"geo_population_d1_pi":0,"geo_population_d1_two":243,"geo_population_d1_white":8004,"geo_population_d1_unk":0,"geo_population_d2_male":10458,"geo_population_d2_female":4900,"geo_medincome":71985,"geo_households":2731,"geo_pctba":0.2116,"metric190_d1_native":0,"metric190_d1_asian":0,"metric190_d1_black":0.35,"metric190_d1_hispanic":0.02,"metric190_d1_pi":0,"metric190_d1_two":0.03,"metric190_d1_white":0.6,"metric190_d1_unk":0,"metric50_d7_less_than_10k":0.037,"metric50_d7_10k_to_15k":0.037,"metric50_d7_15k_to_25k":0.076,"metric50_d7_25k_to_35k":0.124,"metric50_d7_35k_to_50k":0.16,"metric50_d7_50k_to_65k":0.179,"metric50_d7_65k_to_75k":0.135,"metric50_d7_75k_to_100k":0.105,"metric50_d7_more_than_100k":0.147},{"geoid":"22127","geo_population":13665,"geo_population_d1_native":19,"geo_population_d1_asian":34,"geo_population_d1_black":4064,"geo_population_d1_hispanic":444,"geo_population_d1_pi":0,"geo_population_d1_two":211,"geo_population_d1_white":8885,"geo_population_d1_unk":8,"geo_population_d2_male":7258,"geo_population_d2_female":6407,"geo_medincome":44922,"geo_households":3237,"geo_pctba":0.1327,"metric190_d1_native":0,"metric190_d1_asian":0,"metric190_d1_black":0.34,"metric190_d1_hispanic":0.03,"metric190_d1_pi":0,"metric190_d1_two":0.03,"metric190_d1_white":0.6,"metric190_d1_unk":0,"metric50_d7_less_than_10k":0.015,"metric50_d7_10k_to_15k":0.042,"metric50_d7_15k_to_25k":0.129,"metric50_d7_25k_to_35k":0.152,"metric50_d7_35k_to_50k":0.23,"metric50_d7_50k_to_65k":0.166,"metric50_d7_65k_to_75k":0.056,"metric50_d7_75k_to_100k":0.094,"metric50_d7_more_than_100k":0.115}]
