{"type":"Topology","objects":{"tracts":{"type":"GeometryCollection","geometries":[{"type":"Polygon","arcs":[[0,1,2,3]],"properties":{"GEOID":"53061041606"}},{"type":"Polygon","arcs":[[4,5,6,7,8,9,10]],"properties":{"GEOID":"53061041400"}},{"type":"Polygon","arcs":[[11,12,13,14]],"properties":{"GEOID":"53061050102"}},{"type":"Polygon","arcs":[[15,16,17,18]],"properties":{"GEOID":"53061041301"}},{"type":"Polygon","arcs":[[19,20,21,22]],"properties":{"GEOID":"53061051100"}},{"type":"Polygon","arcs":[[23,24,25,26]],"properties":{"GEOID":"53061040200"}},{"type":"Polygon","arcs":[[27,28,29,30]],"properties":{"GEOID":"53061052905"}},{"type":"Polygon","arcs":[[31,32,33,34]],"properties":{"GEOID":"53061053507"}},{"type":"Polygon","arcs":[[35,36,37]],"properties":{"GEOID":"53061041907"}},{"type":"Polygon","arcs":[[38,39,40]],"properties":{"GEOID":"53061050404"}},{"type":"Polygon","arcs":[[41,42,43,44]],"properties":{"GEOID":"53061041201"}},{"type":"Polygon","arcs":[[45,46,47,48,-13,49]],"properties":{"GEOID":"53061051601"}},{"type":"Polygon","arcs":[[50,51,52]],"properties":{"GEOID":"53061042006"}},{"type":"Polygon","arcs":[[53,-4,54,55]],"properties":{"GEOID":"53061041605"}},{"type":"Polygon","arcs":[[56,57,58,59]],"properties":{"GEOID":"53061051918"}},{"type":"Polygon","arcs":[[60,61,-57,62,63,64]],"properties":{"GEOID":"53061051917"}},{"type":"Polygon","arcs":[[65,66,67,68,69]],"properties":{"GEOID":"53061052708"}},{"type":"Polygon","arcs":[[70,71,72]],"properties":{"GEOID":"53061051928"}},{"type":"Polygon","arcs":[[73,74,75,76,77,78]],"properties":{"GEOID":"53061041808"}},{"type":"Polygon","arcs":[[79,80,81,82,83,84,85,86,87,88]],"properties":{"GEOID":"53061053801"}},{"type":"Polygon","arcs":[[89,90,-83,91]],"properties":{"GEOID":"53061053700"}},{"type":"Polygon","arcs":[[92,93,94,95,96,-40,97]],"properties":{"GEOID":"53061050402"}},{"type":"Polygon","arcs":[[98,-72,99,100,101,102,103]],"properties":{"GEOID":"53061041703"}},{"type":"Polygon","arcs":[[104,-22,105,106,107]],"properties":{"GEOID":"53061051302"}},{"type":"Polygon","arcs":[[-3,108,109,110,111,112]],"properties":{"GEOID":"53061041609"}},{"type":"Polygon","arcs":[[113,114,-79,115,116]],"properties":{"GEOID":"53061041813"}},{"type":"Polygon","arcs":[[117,118,119,-109,120]],"properties":{"GEOID":"53061052008"}},{"type":"Polygon","arcs":[[121,122,123]],"properties":{"GEOID":"53061051936"}},{"type":"Polygon","arcs":[[124,125,126,127,128]],"properties":{"GEOID":"53061040800"}},{"type":"Polygon","arcs":[[129,130,131,132,133,-90,134]],"properties":{"GEOID":"53061053506"}},{"type":"Polygon","arcs":[[-30,135,136,-70,137,138,139]],"properties":{"GEOID":"53061052906"}},{"type":"Polygon","arcs":[[140,141,-74,-115]],"properties":{"GEOID":"53061041809"}},{"type":"Polygon","arcs":[[142,143,144,145]],"properties":{"GEOID":"53061042003"}},{"type":"Polygon","arcs":[[-128,146,-9,147,148,149,150]],"properties":{"GEOID":"53061040700"}},{"type":"Polygon","arcs":[[151,152,153,154,155,156,157,158]],"properties":{"GEOID":"53061051402"}},{"type":"Polygon","arcs":[[159,160,161,162,163]],"properties":{"GEOID":"53061052007"}},{"type":"Polygon","arcs":[[-117,164,165,166,-6,167,168,169]],"properties":{"GEOID":"53061041805"}},{"type":"Polygon","arcs":[[170,171,172,173,-84,-91,-134,174,175]],"properties":{"GEOID":"53061053606"}},{"type":"Polygon","arcs":[[-116,-78,176,-165]],"properties":{"GEOID":"53061041814"}},{"type":"Polygon","arcs":[[177,178,179,180,181]],"properties":{"GEOID":"53061052809"}},{"type":"Polygon","arcs":[[182,-158,183]],"properties":{"GEOID":"53061051702"}},{"type":"Polygon","arcs":[[-19,184,185,186,187,188,189]],"properties":{"GEOID":"53061041304"}},{"type":"Polygon","arcs":[[190,191,-59,192,193,194]],"properties":{"GEOID":"53061051938"}},{"type":"Polygon","arcs":[[195,-34,196,197,198]],"properties":{"GEOID":"53061053511"}},{"type":"Polygon","arcs":[[199,200,-159,-183,201,-48,202]],"properties":{"GEOID":"53061051701"}},{"type":"Polygon","arcs":[[203,204,205,206,207,208,209]],"properties":{"GEOID":"53061041812"}},{"type":"Polygon","arcs":[[210,211,212,213,214]],"properties":{"GEOID":"53061052401"}},{"type":"Polygon","arcs":[[215,216,-152,-201,217,-96]],"properties":{"GEOID":"53061051401"}},{"type":"Polygon","arcs":[[-38,218,-169,219,220]],"properties":{"GEOID":"53061041904"}},{"type":"Polygon","arcs":[[221,222,223,224]],"properties":{"GEOID":"53061050600"}},{"type":"Polygon","arcs":[[225,-139,226,-179]],"properties":{"GEOID":"53061052810"}},{"type":"Polygon","arcs":[[227,-86,228]],"properties":{"GEOID":"53061053802"}},{"type":"Polygon","arcs":[[229,230,-87,-228,231,-173,232]],"properties":{"GEOID":"53061052207"}},{"type":"Polygon","arcs":[[233,-10,-147,-127,234]],"properties":{"GEOID":"53061041000"}},{"type":"Polygon","arcs":[[235,236,237,-66,-137]],"properties":{"GEOID":"53061052904"}},{"type":"Polygon","arcs":[[238,239,240,-130,241]],"properties":{"GEOID":"53061053400"}},{"type":"Polygon","arcs":[[242,243,244,245]],"properties":{"GEOID":"53061052112"}},{"type":"Polygon","arcs":[[246,-31,-140,-226,-178,247]],"properties":{"GEOID":"53061052805"}},{"type":"Polygon","arcs":[[248,249,250,-175,-133,251]],"properties":{"GEOID":"53061053604"}},{"type":"Polygon","arcs":[[252,253,254,255,256,257]],"properties":{"GEOID":"53061052114"}},{"type":"Polygon","arcs":[[-77,258,-1,-54,259,-166,-177]],"properties":{"GEOID":"53061041701"}},{"type":"Polygon","arcs":[[260,261,262,263,264,265]],"properties":{"GEOID":"53061050300"}},{"type":"Polygon","arcs":[[266,267,268,-216,-95,269]],"properties":{"GEOID":"53061050900"}},{"type":"Polygon","arcs":[[-145,-15,-204,270,271]],"properties":{"GEOID":"53061042004"}},{"type":"Polygon","arcs":[[272,273,-244,274]],"properties":{"GEOID":"53061051912"}},{"type":"Polygon","arcs":[[275,-275,-243,276,277]],"properties":{"GEOID":"53061052108"}},{"type":"Polygon","arcs":[[278,279,280,281,-197,-33]],"properties":{"GEOID":"53061052701"}},{"type":"Polygon","arcs":[[282,283,284,285,-279,286]],"properties":{"GEOID":"53061052803"}},{"type":"Polygon","arcs":[[287,288,289,-28,-247,290,-284,291,292]],"properties":{"GEOID":"53061940001"}},{"type":"Polygon","arcs":[[293,294,295,296,297,-277,298,-80,299,300,301,302,-212,303,304,305]],"properties":{"GEOID":"53061052105"}},{"type":"Polygon","arcs":[[306,-293,307,308]],"properties":{"GEOID":"53061940002"}},{"type":"Polygon","arcs":[[-101,309,310,311,312,-259,313]],"properties":{"GEOID":"53061041704"}},{"type":"Polygon","arcs":[[-49,-202,-184,-157,314,315,-73,-99,316,317]],"properties":{"GEOID":"53061051802"}},{"type":"Polygon","arcs":[[318,319,320,321]],"properties":{"GEOID":"53061052706"}},{"type":"Polygon","arcs":[[322,323,324,-191,325,326]],"properties":{"GEOID":"53061051922"}},{"type":"Polygon","arcs":[[-89,327,328,329,-300]],"properties":{"GEOID":"53061052211"}},{"type":"Polygon","arcs":[[-255,330,-278,-298,331,332]],"properties":{"GEOID":"53061052122"}},{"type":"Polygon","arcs":[[333,334,335,-156]],"properties":{"GEOID":"53061051929"}},{"type":"Polygon","arcs":[[-291,-248,-182,336,-285]],"properties":{"GEOID":"53061052807"}},{"type":"Polygon","arcs":[[-263,337,-98,-39,338]],"properties":{"GEOID":"53061050403"}},{"type":"Polygon","arcs":[[339,-199,340,-131,-241]],"properties":{"GEOID":"53061053510"}},{"type":"Polygon","arcs":[[341,342,-258,-119]],"properties":{"GEOID":"53061052010"}},{"type":"Polygon","arcs":[[343,344,-233,-172,345]],"properties":{"GEOID":"53061052206"}},{"type":"Polygon","arcs":[[-301,-330,346,347,348]],"properties":{"GEOID":"53061052204"}},{"type":"Polygon","arcs":[[349,350,-141,-114,-170,-219,-37,351]],"properties":{"GEOID":"53061041905"}},{"type":"Polygon","arcs":[[-107,352,-61,353,354]],"properties":{"GEOID":"53061051914"}},{"type":"Polygon","arcs":[[355,356,357,358,359,360,361,-321]],"properties":{"GEOID":"53061052604"}},{"type":"Polygon","arcs":[[-290,362,-236,-136,-29]],"properties":{"GEOID":"53061052903"}},{"type":"Polygon","arcs":[[363,364,365,366,-359]],"properties":{"GEOID":"53061052607"}},{"type":"Polygon","arcs":[[-232,-229,-85,-174]],"properties":{"GEOID":"53061053803"}},{"type":"Polygon","arcs":[[367,368,-63,-60,-192,-325]],"properties":{"GEOID":"53061051916"}},{"type":"Polygon","arcs":[[-313,369,-121,-2]],"properties":{"GEOID":"53061052004"}},{"type":"Polygon","arcs":[[370,-348,371,372,-230,-345]],"properties":{"GEOID":"53061052203"}},{"type":"Polygon","arcs":[[373,374,375,-239,376]],"properties":{"GEOID":"53061053302"}},{"type":"Polygon","arcs":[[377,-215,378,-346,-171,379,380,-366]],"properties":{"GEOID":"53061052301"}},{"type":"Polygon","arcs":[[381,382,383,384,-375,385]],"properties":{"GEOID":"53061053201"}},{"type":"Polygon","arcs":[[386,-163,387,-342]],"properties":{"GEOID":"53061052006"}},{"type":"Polygon","arcs":[[-246,388,-81,-299]],"properties":{"GEOID":"53061052113"}},{"type":"Polygon","arcs":[[-180,-227,-138,-69,389,-249,390,-281]],"properties":{"GEOID":"53061052709"}},{"type":"Polygon","arcs":[[391,-287,-32,392]],"properties":{"GEOID":"53061053509"}},{"type":"Polygon","arcs":[[-316,393,-323,394,395,-310,-100,-71]],"properties":{"GEOID":"53061051927"}},{"type":"Polygon","arcs":[[396,-309,397,-383]],"properties":{"GEOID":"53061053202"}},{"type":"Polygon","arcs":[[-167,-260,-56,398,-294,399,-7]],"properties":{"GEOID":"53061041601"}},{"type":"Polygon","arcs":[[-223,400,-267,401,402]],"properties":{"GEOID":"53061050700"}},{"type":"Polygon","arcs":[[-264,-339,-41,-97,-218,-200,403,404]],"properties":{"GEOID":"53061051500"}},{"type":"Polygon","arcs":[[405,-402,-270,-94]],"properties":{"GEOID":"53061050800"}},{"type":"Polygon","arcs":[[-269,406,-20,407,-153,-217]],"properties":{"GEOID":"53061051000"}},{"type":"Polygon","arcs":[[-318,408,-205,-14]],"properties":{"GEOID":"53061051803"}},{"type":"Polygon","arcs":[[-189,409,-45,410,-235,-126,411]],"properties":{"GEOID":"53061040900"}},{"type":"Polygon","arcs":[[-8,-400,-306,412,-148]],"properties":{"GEOID":"53061041500"}},{"type":"Polygon","arcs":[[-150,413,-25,414,415]],"properties":{"GEOID":"53061040500"}},{"type":"Polygon","arcs":[[416,-108,-355,417,-334,-155]],"properties":{"GEOID":"53061051301"}},{"type":"Polygon","arcs":[[-336,418,419,-394,-315]],"properties":{"GEOID":"53061051930"}},{"type":"Polygon","arcs":[[420,421,422,-67,-238]],"properties":{"GEOID":"53061052710"}},{"type":"Polygon","arcs":[[423,-64,-369,424]],"properties":{"GEOID":"53061051932"}},{"type":"Polygon","arcs":[[425,-256,-333,426]],"properties":{"GEOID":"53061052120"}},{"type":"Polygon","arcs":[[-208,427,-102,-314,-76,428]],"properties":{"GEOID":"53061041815"}},{"type":"Polygon","arcs":[[-111,429,-427,-332,-297,430]],"properties":{"GEOID":"53061052121"}},{"type":"Polygon","arcs":[[-112,-431,-296,431]],"properties":{"GEOID":"53061041610"}},{"type":"Polygon","arcs":[[-326,-195,432,433,434,-123]],"properties":{"GEOID":"53061051937"}},{"type":"Polygon","arcs":[[-420,-425,-368,-324]],"properties":{"GEOID":"53061051931"}},{"type":"Polygon","arcs":[[-423,435,436,437,-390,-68]],"properties":{"GEOID":"53061052711"}},{"type":"Polygon","arcs":[[-188,438,-42,-410]],"properties":{"GEOID":"53061041303"}},{"type":"Polygon","arcs":[[439,-322,-362,440,-436,-422]],"properties":{"GEOID":"53061052707"}},{"type":"Polygon","arcs":[[-433,-194,441,-273,442]],"properties":{"GEOID":"53061051926"}},{"type":"Polygon","arcs":[[-213,-303,443]],"properties":{"GEOID":"53061052402"}},{"type":"Polygon","arcs":[[444,445,-53,446,-17]],"properties":{"GEOID":"53061042001"}},{"type":"Polygon","arcs":[[447,448,-364,-358,449,450]],"properties":{"GEOID":"53061052504"}},{"type":"Polygon","arcs":[[451,-124,-435,452,453]],"properties":{"GEOID":"53061051935"}},{"type":"Polygon","arcs":[[-120,-257,-426,-430,-110]],"properties":{"GEOID":"53061052119"}},{"type":"Polygon","arcs":[[454,-224,-403,-406,-93,-338,-262]],"properties":{"GEOID":"53061050502"}},{"type":"Polygon","arcs":[[-312,455,-164,-387,-118,-370]],"properties":{"GEOID":"53061052005"}},{"type":"Polygon","arcs":[[-395,-327,-122,-452,456]],"properties":{"GEOID":"53061051921"}},{"type":"Polygon","arcs":[[457,458]],"properties":{"GEOID":"53061052605"}},{"type":"Polygon","arcs":[[459,-386,-374]],"properties":{"GEOID":"53061053301"}},{"type":"Polygon","arcs":[[460,-393,-35,-196,-340,-240]],"properties":{"GEOID":"53061053508"}},{"type":"Polygon","arcs":[[461,-129,-151,-416,462,463]],"properties":{"GEOID":"53061040400"}},{"type":"Polygon","arcs":[[-453,-434,-443,-276,-331,-254,464,465]],"properties":{"GEOID":"53061052107"}},{"type":"Polygon","arcs":[[466,467,-26,-414,-149,-413,-305,468,-448,469,-319,-440,-421,-237,-363,-289]],"properties":{"GEOID":"53061052104"}},{"type":"Polygon","arcs":[[-351,-209,-429,-75,-142]],"properties":{"GEOID":"53061041810"}},{"type":"Polygon","arcs":[[-444,-302,-349,-371,-344,-379,-214]],"properties":{"GEOID":"53061052302"}},{"type":"Polygon","arcs":[[-385,470,-392,-461,-376]],"properties":{"GEOID":"53061053101"}},{"type":"Polygon","arcs":[[-447,-52,471,-271,-210,-350,472,-185,-18]],"properties":{"GEOID":"53061041901"}},{"type":"Polygon","arcs":[[473,-146,-272,-472,-51,-446]],"properties":{"GEOID":"53061042005"}},{"type":"Polygon","arcs":[[-437,-441,-361,-458,474,475]],"properties":{"GEOID":"53061052603"}},{"type":"Polygon","arcs":[[476,-464,477,-27,-468]],"properties":{"GEOID":"53061040100"}},{"type":"Polygon","arcs":[[-55,-113,-432,-295,-399]],"properties":{"GEOID":"53061041607"}},{"type":"Polygon","arcs":[[-360,-367,478,-475,-459]],"properties":{"GEOID":"53061052606"}},{"type":"Polygon","arcs":[[479,480,-50,-12,-144]],"properties":{"GEOID":"53061050101"}},{"type":"Polygon","arcs":[[-265,-405,481,-46,-481,482]],"properties":{"GEOID":"53061050200"}},{"type":"Polygon","arcs":[[-404,-203,-47,-482]],"properties":{"GEOID":"53061051602"}},{"type":"Polygon","arcs":[[-187,-220,-168,-5,483,-43,-439]],"properties":{"GEOID":"53061041202"}},{"type":"Polygon","arcs":[[-207,484,-103,-428]],"properties":{"GEOID":"53061041816"}},{"type":"Polygon","arcs":[[485,-380,-176,-251]],"properties":{"GEOID":"53061053605"}},{"type":"Polygon","arcs":[[-470,-451,486,-356,-320]],"properties":{"GEOID":"53061052505"}},{"type":"Polygon","arcs":[[487,-225,-455,-261]],"properties":{"GEOID":"53061050501"}},{"type":"Polygon","arcs":[[-286,-337,-181,-280]],"properties":{"GEOID":"53061052808"}},{"type":"Polygon","arcs":[[-161,488,-454,-466]],"properties":{"GEOID":"53061051934"}},{"type":"Polygon","arcs":[[-418,-354,-65,-424,-419,-335]],"properties":{"GEOID":"53061051913"}},{"type":"Polygon","arcs":[[-132,-341,-198,-282,-391,-252]],"properties":{"GEOID":"53061053505"}},{"type":"Polygon","arcs":[[-438,-476,-479,-381,-486,-250]],"properties":{"GEOID":"53061053603"}},{"type":"Polygon","arcs":[[-328,-88,-231,-373,489]],"properties":{"GEOID":"53061052210"}},{"type":"Polygon","arcs":[[-411,-44,-484,-11,-234]],"properties":{"GEOID":"53061041100"}},{"type":"Polygon","arcs":[[-473,-352,-36,-221,-186]],"properties":{"GEOID":"53061041906"}},{"type":"Polygon","arcs":[[-396,-457,-489,-160,-456,-311]],"properties":{"GEOID":"53061051933"}},{"type":"Polygon","arcs":[[-469,-304,-211,-378,-365,-449]],"properties":{"GEOID":"53061052502"}},{"type":"Polygon","arcs":[[-329,-490,-372,-347]],"properties":{"GEOID":"53061052208"}},{"type":"Polygon","arcs":[[-409,-317,-104,-485,-206]],"properties":{"GEOID":"53061051804"}},{"type":"Polygon","arcs":[[-398,-308,-292,-283,-471,-384]],"properties":{"GEOID":"53061053102"}},{"type":"Polygon","arcs":[[-478,-463,-415,-24]],"properties":{"GEOID":"53061040300"}},{"type":"Polygon","arcs":[[-343,-388,-162,-465,-253]],"properties":{"GEOID":"53061052009"}},{"type":"Polygon","arcs":[[-408,-23,-105,-417,-154]],"properties":{"GEOID":"53061051200"}},{"type":"Polygon","arcs":[[-487,-450,-357]],"properties":{"GEOID":"53061052506"}}]}},"arcs":[[[-122.203617,47.892917],[-122.206856,47.878178]],[[-122.206856,47.878178],[-122.18533,47.877953]],[[-122.18533,47.877953],[-122.185433,47.892488]],[[-122.185433,47.892488],[-122.203617,47.892917]],[[-122.210705,47.936243],[-122.208132,47.920093]],[[-122.208132,47.920093],[-122.20646,47.918921]],[[-122.20646,47.918921],[-122.199755,47.928512]],[[-122.199755,47.928512],[-122.199086,47.96433]],[[-122.199086,47.96433],[-122.200882,47.964396]],[[-122.200882,47.964396],[-122.206566,47.949449]],[[-122.206566,47.949449],[-122.210705,47.936243]],[[-122.303623,47.864433],[-122.303664,47.850202]],[[-122.303664,47.850202],[-122.293174,47.850191]],[[-122.293174,47.850191],[-122.28192,47.864184]],[[-122.28192,47.864184],[-122.303623,47.864433]],[[-122.291111,47.952052],[-122.307048,47.949117],[-122.3121843,47.9237048]],[[-122.3121843,47.9237048],[-122.300164,47.922006]],[[-122.300164,47.922006],[-122.287802,47.924515]],[[-122.287802,47.924515],[-122.291111,47.952052]],[[-122.316128,47.791707],[-122.317652,47.777618]],[[-122.317652,47.777618],[-122.297594,47.77742]],[[-122.297594,47.77742],[-122.297665,47.789798]],[[-122.297665,47.789798],[-122.316128,47.791707]],[[-122.201034,48.000287],[-122.192074,47.992281]],[[-122.192074,47.992281],[-122.180025,47.993096]],[[-122.180025,47.993096],[-122.187466,48.017084]],[[-122.187466,48.017084],[-122.201034,48.000287]],[[-122.183819,48.068141],[-122.183944,48.061294]],[[-122.183944,48.061294],[-122.162249,48.061195]],[[-122.162249,48.061195],[-122.16553,48.075477]],[[-122.16553,48.075477],[-122.183819,48.068141]],[[-122.140459,48.180894],[-122.140567,48.151893]],[[-122.140567,48.151893],[-122.113243,48.15163]],[[-122.113243,48.15163],[-122.129006,48.18081]],[[-122.129006,48.18081],[-122.140459,48.180894]],[[-122.244545,47.921818],[-122.257951,47.907431]],[[-122.257951,47.907431],[-122.24664,47.907337]],[[-122.24664,47.907337],[-122.244545,47.921818]],[[-122.337075,47.818733],[-122.346588,47.806942]],[[-122.346588,47.806942],[-122.330155,47.806882]],[[-122.330155,47.806882],[-122.337075,47.818733]],[[-122.246369,47.951293],[-122.231782,47.936466]],[[-122.231782,47.936466],[-122.228374,47.936525]],[[-122.228374,47.936525],[-122.230895,47.951749]],[[-122.230895,47.951749],[-122.246369,47.951293]],[[-122.309458,47.850836],[-122.324826,47.839237]],[[-122.324826,47.839237],[-122.299553,47.839167]],[[-122.299553,47.839167],[-122.29463,47.84659]],[[-122.29463,47.84659],[-122.293174,47.850191]],[[-122.303664,47.850202],[-122.309458,47.850836]],[[-122.308264,47.895524],[-122.284971,47.889956]],[[-122.284971,47.889956],[-122.29296,47.905139]],[[-122.29296,47.905139],[-122.308264,47.895524]],[[-122.20704,47.907284],[-122.203617,47.892917]],[[-122.185433,47.892488],[-122.185452,47.907022]],[[-122.185452,47.907022],[-122.20704,47.907284]],[[-122.232988,47.791354],[-122.233039,47.776816]],[[-122.233039,47.776816],[-122.19121,47.776408]],[[-122.19121,47.776408],[-122.207061,47.791384]],[[-122.207061,47.791384],[-122.232988,47.791354]],[[-122.25691,47.787362],[-122.260683,47.777083]],[[-122.260683,47.777083],[-122.233039,47.776816]],[[-122.232988,47.791354],[-122.238361,47.791426]],[[-122.238361,47.791426],[-122.25549,47.79157]],[[-122.25549,47.79157],[-122.25691,47.787362]],[[-122.14087,48.064459],[-122.140892,48.053674]],[[-122.140892,48.053674],[-122.11947,48.053557]],[[-122.11947,48.053557],[-122.119034,48.072018]],[[-122.119034,48.072018],[-122.140224,48.071749]],[[-122.140224,48.071749],[-122.14087,48.064459]],[[-122.261052,47.835044],[-122.235697,47.838688],[-122.235812,47.849432]],[[-122.235812,47.849432],[-122.257295,47.849813]],[[-122.257295,47.849813],[-122.261052,47.835044]],[[-122.238926,47.89647],[-122.238815,47.885591]],[[-122.238815,47.885591],[-122.238814,47.881905]],[[-122.238814,47.881905],[-122.234087,47.881922]],[[-122.234087,47.881922],[-122.216578,47.896427]],[[-122.216578,47.896427],[-122.233557,47.896493]],[[-122.233557,47.896493],[-122.238926,47.89647]],[[-122.04685,47.83137],[-122.047575,47.831301]],[[-122.047575,47.831301],[-122.035991,47.822186],[-122.01537,47.817067],[-121.967791,47.776183]],[[-121.967791,47.776183],[-121.840692,47.777366],[-121.584541,47.777054],[-121.455535,47.780576],[-121.195672,47.779144],[-121.119179,47.779933],[-121.092571,47.800725],[-121.070685,47.826616],[-121.080222,47.834123],[-121.106932,47.828974],[-121.134343,47.843044],[-121.158264,47.876644],[-121.180776,47.898769],[-121.171361,47.913296],[-121.164968,47.954505],[-121.140026,47.983416]],[[-121.140026,47.983416],[-121.145884,48.013049],[-121.178384,48.023983],[-121.21083,48.040589],[-121.255534,48.046936],[-121.290982,48.058194],[-121.316992,48.088405],[-121.35036,48.095799],[-121.383821,48.096213],[-121.389986,48.082509],[-121.425973,48.056587],[-121.444071,48.026164]],[[-121.444071,48.026164],[-121.438525,48.001207],[-121.44411,47.986054],[-121.50347,47.984894],[-121.537766,47.99589],[-121.555643,47.995595],[-121.568944,47.979519]],[[-121.568944,47.979519],[-121.549945,47.964192],[-121.539059,47.937521],[-121.521721,47.928382],[-121.536046,47.915714],[-121.528741,47.89188],[-121.551076,47.876849],[-121.546271,47.868535],[-121.587001,47.85219],[-121.602636,47.841039],[-121.661636,47.834274],[-121.694822,47.850449],[-121.751032,47.859735],[-121.763838,47.853648],[-121.798077,47.859263]],[[-121.798077,47.859263],[-121.848179,47.838732],[-121.871896,47.845618]],[[-121.871896,47.845618],[-121.895113,47.854265],[-121.917082,47.842519],[-121.95497,47.854588]],[[-121.95497,47.854588],[-121.990561,47.839279]],[[-121.990561,47.839279],[-121.995212,47.82943],[-122.031982,47.82275],[-122.04685,47.83137]],[[-121.856602,48.297491],[-121.840961,48.283846],[-121.90201,48.258868],[-121.917672,48.262345],[-121.949359,48.227087],[-121.924321,48.200297],[-121.842459,48.182228],[-121.815479,48.161084],[-121.852348,48.136677]],[[-121.852348,48.136677],[-121.84604,48.12963],[-121.757011,48.117978],[-121.725133,48.109505],[-121.71573,48.075226],[-121.631629,48.065762],[-121.581035,48.074419],[-121.539455,48.085804],[-121.478439,48.046889],[-121.450144,48.040521],[-121.444071,48.026164]],[[-121.140026,47.983416],[-121.118183,47.997103],[-121.129221,48.019826],[-121.15326,48.039693],[-121.130519,48.04518],[-121.115976,48.057963],[-121.036217,48.076838],[-121.015942,48.074795],[-120.98045,48.095189],[-120.952628,48.117223],[-120.965619,48.140333],[-120.948421,48.155032],[-120.907425,48.163184],[-120.920588,48.187311],[-120.964769,48.211328],[-120.959848,48.227769],[-121.011263,48.278191],[-121.001658,48.296009],[-121.444964,48.296038],[-121.636419,48.298473],[-121.76255,48.29886],[-121.856602,48.297491]],[[-122.366939,47.8105],[-122.366853,47.799585]],[[-122.366853,47.799585],[-122.33566,47.79968]],[[-122.33566,47.79968],[-122.331612,47.799652]],[[-122.331612,47.799652],[-122.326653,47.806843]],[[-122.326653,47.806843],[-122.330155,47.806882]],[[-122.346588,47.806942],[-122.366939,47.8105]],[[-122.257795,47.849821],[-122.257295,47.849813]],[[-122.235812,47.849432],[-122.231965,47.849337]],[[-122.231965,47.849337],[-122.230118,47.873999],[-122.240233,47.877017]],[[-122.240233,47.877017],[-122.244299,47.872431]],[[-122.244299,47.872431],[-122.246067,47.865486]],[[-122.246067,47.865486],[-122.257795,47.849821]],[[-122.297682,47.795145],[-122.297665,47.789798]],[[-122.297594,47.77742],[-122.286863,47.777322]],[[-122.286863,47.777322],[-122.286224,47.791843]],[[-122.286224,47.791843],[-122.297682,47.795145]],[[-122.18533,47.877953],[-122.170331,47.874683]],[[-122.170331,47.874683],[-122.165973,47.877758]],[[-122.165973,47.877758],[-122.163743,47.879494]],[[-122.163743,47.879494],[-122.170765,47.888872]],[[-122.170765,47.888872],[-122.185433,47.892488]],[[-122.244625,47.904189],[-122.25184,47.896448]],[[-122.25184,47.896448],[-122.238926,47.89647]],[[-122.233557,47.896493],[-122.228234,47.908284]],[[-122.228234,47.908284],[-122.244625,47.904189]],[[-122.185429,47.868438],[-122.186045,47.860444]],[[-122.186045,47.860444],[-122.168995,47.86306]],[[-122.168995,47.86306],[-122.170331,47.874683]],[[-122.18533,47.877953],[-122.185429,47.868438]],[[-122.207469,47.820258],[-122.207689,47.809412]],[[-122.207689,47.809412],[-122.192234,47.812931]],[[-122.192234,47.812931],[-122.207469,47.820258]],[[-122.2319367,47.9832],[-122.2306916,47.9704385]],[[-122.2306916,47.9704385],[-122.217336,47.97111]],[[-122.217336,47.97111],[-122.212591,47.971172]],[[-122.212591,47.971172],[-122.205706,47.98323]],[[-122.205706,47.98323],[-122.2319367,47.9832]],[[-121.998625,48.297499],[-122.006198,48.272706],[-122.029846,48.2771],[-122.050659,48.25098],[-122.084167,48.244587],[-122.1277,48.203597]],[[-122.1277,48.203597],[-122.118694,48.200697]],[[-122.118694,48.200697],[-122.076064,48.191546],[-122.078284,48.181512],[-122.055898,48.155404],[-122.015892,48.136503],[-121.999434,48.110413],[-121.974364,48.095477]],[[-121.974364,48.095477],[-121.971084,48.097253]],[[-121.971084,48.097253],[-121.952393,48.119662],[-121.914864,48.118824],[-121.89756,48.125824],[-121.861825,48.123378],[-121.852348,48.136677]],[[-121.856602,48.297491],[-121.998625,48.297499]],[[-122.162249,48.061195],[-122.156929,48.06102]],[[-122.156929,48.06102],[-122.14087,48.064459]],[[-122.140224,48.071749],[-122.140005,48.07438]],[[-122.140005,48.07438],[-122.162294,48.075423]],[[-122.162294,48.075423],[-122.16553,48.075477]],[[-122.25184,47.896448],[-122.257239,47.890694]],[[-122.257239,47.890694],[-122.238815,47.885591]],[[-122.3329007,47.8793146],[-122.33309,47.864766]],[[-122.33309,47.864766],[-122.303623,47.864433]],[[-122.303623,47.864433],[-122.303682,47.871546]],[[-122.303682,47.871546],[-122.3329007,47.8793146]],[[-122.212591,47.971172],[-122.200882,47.964396]],[[-122.199086,47.96433],[-122.188953,47.965747]],[[-122.188953,47.965747],[-122.186196,47.976465]],[[-122.186196,47.976465],[-122.192266,47.984385]],[[-122.192266,47.984385],[-122.205706,47.98323]],[[-122.311071,47.8212],[-122.314392,47.806668]],[[-122.314392,47.806668],[-122.305797,47.806533]],[[-122.305797,47.806533],[-122.297793,47.80649]],[[-122.297793,47.80649],[-122.292337,47.806436]],[[-122.292337,47.806436],[-122.279594,47.82094]],[[-122.279594,47.82094],[-122.28109,47.820953]],[[-122.28109,47.820953],[-122.292382,47.82099]],[[-122.292382,47.82099],[-122.311071,47.8212]],[[-122.21587,47.844337],[-122.210766,47.83463]],[[-122.210766,47.83463],[-122.185776,47.834553]],[[-122.185776,47.834553],[-122.185561,47.845371]],[[-122.185561,47.845371],[-122.209812,47.845322]],[[-122.209812,47.845322],[-122.21587,47.844337]],[[-122.228234,47.908284],[-122.211842,47.907176]],[[-122.211842,47.907176],[-122.210939,47.907249]],[[-122.210939,47.907249],[-122.20646,47.918921]],[[-122.208132,47.920093],[-122.227018,47.923051]],[[-122.227018,47.923051],[-122.241676,47.907332]],[[-122.241676,47.907332],[-122.244625,47.904189]],[[-121.973336,47.982017],[-121.969523,47.962695]],[[-121.969523,47.962695],[-121.946776,47.957667],[-121.923543,47.965576],[-121.889834,47.951913]],[[-121.889834,47.951913],[-121.859426,47.962788],[-121.835493,47.950013]],[[-121.835493,47.950013],[-121.777032,47.950001],[-121.764357,47.973434],[-121.736605,47.96866],[-121.682862,47.975972],[-121.642035,47.972304],[-121.627461,47.979413],[-121.568944,47.979519]],[[-121.971084,48.097253],[-121.964087,48.07982]],[[-121.964087,48.07982],[-121.943731,48.075095],[-121.914418,48.035843],[-121.918219,48.014132],[-121.955253,48.011153],[-121.961314,47.98767],[-121.973336,47.982017]],[[-122.216578,47.896427],[-122.211842,47.907176]],[[-122.162432,48.092531],[-122.162239,48.085735]],[[-122.162239,48.085735],[-122.140089,48.084894]],[[-122.140089,48.084894],[-122.140546,48.091959]],[[-122.140546,48.091959],[-122.156583,48.092218]],[[-122.156583,48.092218],[-122.162432,48.092531]],[[-122.292519,47.842815],[-122.292382,47.82099]],[[-122.28109,47.820953],[-122.292519,47.842815]],[[-122.287802,47.924515],[-122.271949,47.922109]],[[-122.271949,47.922109],[-122.240437,47.923495]],[[-122.240437,47.923495],[-122.240446,47.92417]],[[-122.240446,47.92417],[-122.257432,47.943114],[-122.258595,47.95717]],[[-122.258595,47.95717],[-122.2597487,47.958401]],[[-122.2597487,47.958401],[-122.291111,47.952052]],[[-122.212019,47.798554],[-122.214171,47.794978]],[[-122.214171,47.794978],[-122.207061,47.791384]],[[-122.19121,47.776408],[-122.169443,47.776259]],[[-122.169443,47.776259],[-122.181218,47.791034]],[[-122.181218,47.791034],[-122.212019,47.798554]],[[-122.128888,48.182967],[-122.129006,48.18081]],[[-122.113243,48.15163],[-122.090996,48.144481]],[[-122.090996,48.144481],[-122.1024,48.176987],[-122.098103,48.187145]],[[-122.098103,48.187145],[-122.128888,48.182967]],[[-122.308913,47.828354],[-122.315183,47.821214]],[[-122.315183,47.821214],[-122.311071,47.8212]],[[-122.292519,47.842815],[-122.29463,47.84659]],[[-122.299553,47.839167],[-122.308913,47.828354]],[[-122.274677,47.871996],[-122.28192,47.864184]],[[-122.28192,47.864184],[-122.27459,47.864175]],[[-122.27459,47.864175],[-122.268781,47.864136]],[[-122.268781,47.864136],[-122.262344,47.873626]],[[-122.262344,47.873626],[-122.250343,47.881944]],[[-122.250343,47.881944],[-122.258412,47.889419]],[[-122.258412,47.889419],[-122.274677,47.871996]],[[-122.074668,47.936914],[-122.10722,47.929604],[-122.108757,47.912007]],[[-122.108757,47.912007],[-122.09867,47.910634]],[[-122.09867,47.910634],[-122.079532,47.923117]],[[-122.079532,47.923117],[-122.07361,47.934728]],[[-122.07361,47.934728],[-122.074668,47.936914]],[[-122.331612,47.799652],[-122.330141,47.799627]],[[-122.330141,47.799627],[-122.314392,47.806668]],[[-122.315183,47.821214],[-122.326653,47.806843]],[[-122.24664,47.907337],[-122.241676,47.907332]],[[-122.227018,47.923051],[-122.240437,47.923495]],[[-122.240437,47.923495],[-122.244545,47.921818]],[[-122.3949394,47.8033042],[-122.3952033,47.7779218],[-122.377522,47.77785]],[[-122.377522,47.77785],[-122.3765,47.796394]],[[-122.3765,47.796394],[-122.377528,47.799778]],[[-122.377528,47.799778],[-122.3949394,47.8033042]],[[-122.162239,48.085735],[-122.162294,48.075423]],[[-122.140005,48.07438],[-122.140089,48.084894]],[[-121.848697,47.895263],[-121.853185,47.863417],[-121.873607,47.861417],[-121.871896,47.845618]],[[-121.798077,47.859263],[-121.777634,47.878373],[-121.848697,47.895263]],[[-121.932251,47.872107],[-121.961209,47.857221]],[[-121.961209,47.857221],[-121.95497,47.854588]],[[-121.848697,47.895263],[-121.812913,47.917632],[-121.835493,47.950013]],[[-121.889834,47.951913],[-121.900359,47.91792],[-121.909425,47.909569],[-121.919052,47.876005],[-121.932251,47.872107]],[[-122.226118,47.959407],[-122.206566,47.949449]],[[-122.217336,47.97111],[-122.226118,47.959407]],[[-122.156929,48.06102],[-122.164768,48.041701]],[[-122.164768,48.041701],[-122.140985,48.042849]],[[-122.140985,48.042849],[-122.140892,48.053674]],[[-122.251843,48.297462],[-122.247176,48.282048],[-122.226178,48.282255],[-122.210262,48.26808],[-122.210843,48.239436],[-122.240801,48.238821],[-122.219729,48.220102],[-122.209812,48.197079]],[[-122.209812,48.197079],[-122.194916,48.200089],[-122.171914,48.189124],[-122.150944,48.210432],[-122.128194,48.203676]],[[-122.128194,48.203676],[-122.1277,48.203597]],[[-121.998625,48.297499],[-122.251843,48.297462]],[[-122.051277,47.830953],[-122.076983,47.813277],[-122.111454,47.802085]],[[-122.111454,47.802085],[-122.077616,47.788068],[-122.074677,47.775978]],[[-122.074677,47.775978],[-122.054706,47.775678]],[[-122.054706,47.775678],[-122.059664,47.793276],[-122.043303,47.799152],[-122.051277,47.830953]],[[-122.183966,48.100107],[-122.183819,48.068141]],[[-122.162432,48.092531],[-122.183966,48.100107]],[[-122.064645,48.092775],[-122.065004,48.072186]],[[-122.065004,48.072186],[-122.00215,48.072495],[-121.977511,48.075989],[-121.957419,48.054747]],[[-121.957419,48.054747],[-121.964087,48.07982]],[[-121.974364,48.095477],[-122.024835,48.094122],[-122.045585,48.081182],[-122.064645,48.092775]],[[-122.169235,47.856233],[-122.17004,47.834444]],[[-122.17004,47.834444],[-122.150654,47.83419]],[[-122.150654,47.83419],[-122.135104,47.848597],[-122.142343,47.862432]],[[-122.142343,47.862432],[-122.161136,47.863914]],[[-122.161136,47.863914],[-122.168995,47.86306]],[[-122.168995,47.86306],[-122.169235,47.856233]],[[-122.234087,47.881922],[-122.206856,47.878178]],[[-122.20704,47.907284],[-122.210939,47.907249]],[[-122.3776577,47.8177053],[-122.372187,47.817791]],[[-122.372187,47.817791],[-122.367271,47.817986]],[[-122.367271,47.817986],[-122.337244,47.821444]],[[-122.337244,47.821444],[-122.337757,47.831541]],[[-122.337757,47.831541],[-122.3603588,47.8340103]],[[-122.3603588,47.8340103],[-122.3776577,47.8177053]],[[-122.346273,47.77949],[-122.346286,47.777794]],[[-122.346286,47.777794],[-122.327229,47.777657]],[[-122.327229,47.777657],[-122.330141,47.799627]],[[-122.33566,47.79968],[-122.346273,47.77949]],[[-122.274677,47.871996],[-122.280006,47.88266]],[[-122.280006,47.88266],[-122.303682,47.871546]],[[-122.143478,47.804841],[-122.143433,47.78514],[-122.153842,47.776196]],[[-122.153842,47.776196],[-122.074677,47.775978]],[[-122.111454,47.802085],[-122.143478,47.804841]],[[-122.119672,47.844734],[-122.143478,47.804841]],[[-122.051277,47.830953],[-122.064369,47.830078],[-122.092698,47.846425],[-122.094829,47.865053],[-122.109768,47.878113]],[[-122.109768,47.878113],[-122.119672,47.844734]],[[-122.140567,48.151893],[-122.140853,48.113697]],[[-122.140853,48.113697],[-122.140546,48.091959]],[[-122.140546,48.091959],[-122.111847,48.091836],[-122.112355,48.114874],[-122.087021,48.115647]],[[-122.087021,48.115647],[-122.090996,48.144481]],[[-122.188682,48.152378],[-122.185203,48.122982]],[[-122.185203,48.122982],[-122.18415,48.110892]],[[-122.18415,48.110892],[-122.175444,48.111012]],[[-122.175444,48.111012],[-122.140853,48.113697]],[[-122.140567,48.151893],[-122.188682,48.152378]],[[-122.273479,48.056677],[-122.274394,48.04823],[-122.2231916,48.024617]],[[-122.2231916,48.024617],[-122.184262,48.036077],[-122.184125,48.049214]],[[-122.184125,48.049214],[-122.183944,48.061294]],[[-122.183966,48.100107],[-122.18415,48.110892]],[[-122.185203,48.122982],[-122.248331,48.123135]],[[-122.248331,48.123135],[-122.254737,48.104109],[-122.246311,48.081123],[-122.271245,48.070741],[-122.273479,48.056677]],[[-122.189088,47.928443],[-122.173413,47.908638]],[[-122.173413,47.908638],[-122.157208,47.8968]],[[-122.157208,47.8968],[-122.144306,47.891238]],[[-122.144306,47.891238],[-122.134608,47.885955]],[[-122.134608,47.885955],[-122.109768,47.878113]],[[-122.051277,47.830953],[-122.047575,47.831301]],[[-122.04685,47.83137],[-122.028798,47.830164],[-122.013955,47.84228]],[[-122.013955,47.84228],[-122.044367,47.873816],[-122.044961,47.886768]],[[-122.044961,47.886768],[-122.084869,47.902462]],[[-122.084869,47.902462],[-122.09867,47.910634]],[[-122.108757,47.912007],[-122.143298,47.921763]],[[-122.143298,47.921763],[-122.168463,47.928309]],[[-122.168463,47.928309],[-122.189088,47.928443]],[[-122.3634781,48.1233071],[-122.343241,48.097631],[-122.321419,48.080991],[-122.273479,48.056677]],[[-122.248331,48.123135],[-122.296232,48.123245]],[[-122.296232,48.123245],[-122.3634781,48.1233071]],[[-122.231965,47.849337],[-122.222051,47.849386]],[[-122.222051,47.849386],[-122.21743,47.849493]],[[-122.21743,47.849493],[-122.218402,47.854967]],[[-122.218402,47.854967],[-122.206856,47.878178]],[[-122.234087,47.881922],[-122.240233,47.877017]],[[-122.279594,47.82094],[-122.262095,47.831683]],[[-122.262095,47.831683],[-122.261052,47.835044]],[[-122.257795,47.849821],[-122.274236,47.849999]],[[-122.274236,47.849999],[-122.293174,47.850191]],[[-122.134702,48.021621],[-122.126775,48.003144],[-122.137266,47.982947]],[[-122.137266,47.982947],[-122.108218,48.002417]],[[-122.108218,48.002417],[-122.106307,48.002892]],[[-122.106307,48.002892],[-122.109388,48.02146],[-122.134702,48.021621]],[[-122.238505,47.824162],[-122.253891,47.825691]],[[-122.253891,47.825691],[-122.242385,47.820273]],[[-122.242385,47.820273],[-122.214171,47.794978]],[[-122.212019,47.798554],[-122.207689,47.809412]],[[-122.207689,47.809412],[-122.238505,47.824162]],[[-121.990561,47.839279],[-121.993183,47.85047]],[[-121.993183,47.85047],[-122.007255,47.848728]],[[-122.007255,47.848728],[-122.013955,47.84228]],[[-122.150654,47.83419],[-122.119672,47.844734]],[[-122.134608,47.885955],[-122.139899,47.871519]],[[-122.139899,47.871519],[-122.142343,47.862432]],[[-122.292337,47.806436],[-122.281573,47.804117]],[[-122.281573,47.804117],[-122.271484,47.810155]],[[-122.271484,47.810155],[-122.279594,47.82094]],[[-122.156583,48.092218],[-122.154267,48.103724],[-122.175444,48.111012]],[[-122.367271,47.817986],[-122.366939,47.8105]],[[-122.337075,47.818733],[-122.337244,47.821444]],[[-122.128194,48.203676],[-122.128888,48.182967]],[[-122.098103,48.187145],[-122.118694,48.200697]],[[-122.186045,47.860444],[-122.186725,47.84882]],[[-122.186725,47.84882],[-122.169235,47.856233]],[[-121.991789,47.931187],[-121.981595,47.904782]],[[-121.981595,47.904782],[-121.969243,47.900234],[-121.96936,47.881115],[-121.932251,47.872107]],[[-121.969523,47.962695],[-121.980402,47.957991],[-121.978018,47.936676],[-121.991789,47.931187]],[[-122.007255,47.848728],[-121.990696,47.865336]],[[-121.990696,47.865336],[-122.031307,47.881322]],[[-122.031307,47.881322],[-122.044961,47.886768]],[[-122.271199,47.907529],[-122.258412,47.889419]],[[-122.258412,47.889419],[-122.257239,47.890694]],[[-122.257951,47.907431],[-122.271199,47.907529]],[[-122.286863,47.777322],[-122.260683,47.777083]],[[-122.25691,47.787362],[-122.28414,47.791806]],[[-122.28414,47.791806],[-122.286224,47.791843]],[[-122.108218,48.002417],[-122.108736,47.992621]],[[-122.108736,47.992621],[-122.098471,47.978103]],[[-122.098471,47.978103],[-122.091508,47.978186]],[[-122.091508,47.978186],[-122.07671,47.985782]],[[-122.07671,47.985782],[-122.079058,48.005769]],[[-122.079058,48.005769],[-122.096263,48.017324]],[[-122.096263,48.017324],[-122.106307,48.002892]],[[-122.184125,48.049214],[-122.164768,48.041701]],[[-122.091508,47.978186],[-122.101415,47.95183]],[[-122.101415,47.95183],[-122.074459,47.943743]],[[-122.074459,47.943743],[-122.060787,47.972027],[-122.035657,47.986898]],[[-122.035657,47.986898],[-122.07671,47.985782]],[[-122.242385,47.820273],[-122.23849,47.805872]],[[-122.23849,47.805872],[-122.238361,47.791426]],[[-122.218402,47.854967],[-122.208697,47.867119],[-122.185429,47.868438]],[[-121.981595,47.904782],[-122.031307,47.881322]],[[-121.990696,47.865336],[-121.966777,47.85706]],[[-121.966777,47.85706],[-121.961209,47.857221]],[[-122.353205,48.297572],[-122.361295,48.268518],[-122.324211,48.268624],[-122.325412,48.23842],[-122.352576,48.235063]],[[-122.352576,48.235063],[-122.326637,48.213525],[-122.293676,48.211738],[-122.264513,48.198986]],[[-122.264513,48.198986],[-122.25,48.194914],[-122.209812,48.197079]],[[-122.251843,48.297462],[-122.353205,48.297572]],[[-122.074459,47.943743],[-122.074668,47.936914]],[[-122.07361,47.934728],[-122.001681,47.935227],[-121.991789,47.931187]],[[-121.973336,47.982017],[-122.010905,47.997966]],[[-122.010905,47.997966],[-122.035657,47.986898]],[[-122.395536,48.239869],[-122.368319,48.214609],[-122.370275,48.190941],[-122.35747,48.182285],[-122.370172,48.1645467]],[[-122.370172,48.1645467],[-122.289205,48.15572]],[[-122.289205,48.15572],[-122.286494,48.155691]],[[-122.286494,48.155691],[-122.264524,48.174193],[-122.264513,48.198986]],[[-122.352576,48.235063],[-122.395536,48.239869]],[[-122.186045,47.860444],[-122.209812,47.845322]],[[-122.185561,47.845371],[-122.186725,47.84882]],[[-122.054706,47.775678],[-121.967791,47.776183]],[[-122.119034,48.072018],[-122.065004,48.072186]],[[-122.064645,48.092775],[-122.087021,48.115647]],[[-122.191286,48.167061],[-122.188682,48.152378]],[[-122.140459,48.180894],[-122.191286,48.167061]],[[-122.262095,47.831683],[-122.253891,47.825691]],[[-122.238505,47.824162],[-122.220491,47.827919]],[[-122.220491,47.827919],[-122.222051,47.849386]],[[-122.370172,48.1645467],[-122.3634781,48.1233071]],[[-122.296232,48.123245],[-122.28236,48.134464],[-122.289205,48.15572]],[[-122.185452,47.907022],[-122.173413,47.908638]],[[-122.189088,47.928443],[-122.199755,47.928512]],[[-122.377522,47.77785],[-122.346286,47.777794]],[[-122.346273,47.77949],[-122.366773,47.790524]],[[-122.366773,47.790524],[-122.3765,47.796394]],[[-122.308913,47.828354],[-122.330592,47.831088]],[[-122.330592,47.831088],[-122.337757,47.831541]],[[-122.366853,47.799585],[-122.366773,47.790524]],[[-122.327229,47.777657],[-122.317652,47.777618]],[[-122.316128,47.791707],[-122.305797,47.806533]],[[-122.274236,47.849999],[-122.27459,47.864175]],[[-122.258595,47.95717],[-122.246369,47.951293]],[[-122.230895,47.951749],[-122.226118,47.959407]],[[-122.2306916,47.9704385],[-122.2597487,47.958401]],[[-122.168463,47.928309],[-122.188953,47.965747]],[[-122.186196,47.976465],[-122.180025,47.993096]],[[-122.192074,47.992281],[-122.192137,47.989651]],[[-122.192137,47.989651],[-122.192266,47.984385]],[[-122.297793,47.80649],[-122.297682,47.795145]],[[-122.28414,47.791806],[-122.281573,47.804117]],[[-122.271484,47.810155],[-122.254226,47.808314]],[[-122.254226,47.808314],[-122.253891,47.825691]],[[-122.140985,48.042849],[-122.135683,48.03571]],[[-122.135683,48.03571],[-122.125015,48.035736]],[[-122.125015,48.035736],[-122.11947,48.053557]],[[-122.254226,47.808314],[-122.25549,47.79157]],[[-122.23849,47.805872],[-122.254226,47.808314]],[[-122.152384,47.875809],[-122.161136,47.863914]],[[-122.139899,47.871519],[-122.152384,47.875809]],[[-122.262344,47.873626],[-122.244299,47.872431]],[[-122.238814,47.881905],[-122.250343,47.881944]],[[-122.165973,47.877758],[-122.152384,47.875809]],[[-122.144306,47.891238],[-122.163743,47.879494]],[[-122.157208,47.8968],[-122.170765,47.888872]],[[-122.181218,47.791034],[-122.182205,47.813099]],[[-122.182205,47.813099],[-122.182269,47.813114]],[[-122.182269,47.813114],[-122.192234,47.812931]],[[-122.125015,48.035736],[-122.098025,48.034013]],[[-122.098025,48.034013],[-122.08816,48.050237],[-122.065077,48.050444]],[[-122.065077,48.050444],[-122.065004,48.072186]],[[-122.240446,47.92417],[-122.231782,47.936466]],[[-122.135683,48.03571],[-122.134702,48.021621]],[[-122.096263,48.017324],[-122.098025,48.034013]],[[-122.169443,47.776259],[-122.153842,47.776196]],[[-122.143478,47.804841],[-122.182205,47.813099]],[[-122.084869,47.902462],[-122.079532,47.923117]],[[-122.3121843,47.9237048],[-122.3274788,47.8999214]],[[-122.3274788,47.8999214],[-122.308264,47.895524]],[[-122.29296,47.905139],[-122.300164,47.922006]],[[-122.137488,47.97818],[-122.12014,47.949296]],[[-122.12014,47.949296],[-122.101415,47.95183]],[[-122.098471,47.978103],[-122.119447,47.978119]],[[-122.119447,47.978119],[-122.137488,47.97818]],[[-122.207446,47.82388],[-122.207469,47.820258]],[[-122.182269,47.813114],[-122.185889,47.829512]],[[-122.185889,47.829512],[-122.207446,47.82388]],[[-122.372187,47.817791],[-122.377528,47.799778]],[[-122.21743,47.849493],[-122.21587,47.844337]],[[-122.207446,47.82388],[-122.220491,47.827919]],[[-122.053293,48.033546],[-122.078866,48.030149],[-122.079058,48.005769]],[[-122.079058,48.005769],[-122.051642,48.015463],[-122.053293,48.033546]],[[-122.353205,48.297572],[-122.387107,48.273701],[-122.395536,48.239869]],[[-122.209812,48.197079],[-122.191286,48.167061]],[[-122.2296684,47.98869],[-122.2319367,47.9832]],[[-122.192137,47.989651],[-122.206948,47.989826]],[[-122.206948,47.989826],[-122.2296684,47.98869]],[[-122.17004,47.834444],[-122.185776,47.834553]],[[-122.185776,47.834553],[-122.185889,47.829512]],[[-122.2231916,48.024617],[-122.2259364,48.0181887]],[[-122.2259364,48.0181887],[-122.187466,48.017084]],[[-122.143298,47.921763],[-122.154709,47.931393],[-122.14355,47.946683],[-122.12014,47.949296]],[[-122.137488,47.97818],[-122.137266,47.982947]],[[-122.286494,48.155691],[-122.238348,48.151988],[-122.188682,48.152378]],[[-122.284971,47.889956],[-122.280006,47.88266]],[[-122.271199,47.907529],[-122.271949,47.922109]],[[-122.3274788,47.8999214],[-122.3329007,47.8793146]],[[-122.053293,48.033546],[-122.049877,48.036009]],[[-122.049877,48.036009],[-122.065077,48.050444]],[[-122.2259364,48.0181887],[-122.2296684,47.98869]],[[-122.206948,47.989826],[-122.201034,48.000287]],[[-122.035657,47.986898],[-122.032404,48.036028],[-122.049877,48.036009]],[[-122.33309,47.864766],[-122.3349576,47.8599322]],[[-122.3349576,47.8599322],[-122.309458,47.850836]],[[-122.330592,47.831088],[-122.324826,47.839237]],[[-122.3349576,47.8599322],[-122.339944,47.846718],[-122.3603588,47.8340103]],[[-122.210705,47.936243],[-122.228374,47.936525]],[[-122.268781,47.864136],[-122.246067,47.865486]],[[-121.957419,48.054747],[-121.963413,48.038824],[-121.990137,48.039164],[-122.004979,48.024994],[-122.010905,47.997966]],[[-122.119447,47.978119],[-122.108736,47.992621]],[[-122.3776577,47.8177053],[-122.3949394,47.8033042]],[[-122.210766,47.83463],[-122.207446,47.82388]],[[-121.966777,47.85706],[-121.993183,47.85047]]],"bbox":[-122.395536,47.775678,-120.907425,48.29886]}
