{"breaks":[0.844,0.88,0.901,0.918],"data":[{"id":"01","value":0.871},{"id":"02","value":0.917},{"id":"04","value":0.91},{"id":"05","value":0.86},{"id":"06","value":0.934},{"id":"08","value":0.938},{"id":"09","value":0.931},{"id":"10","value":0.924},{"id":"12","value":0.91},{"id":"13","value":0.901},{"id":"15","value":0.926},{"id":"16","value":0.925},{"id":"17","value":0.913},{"id":"18","value":0.897},{"id":"19","value":0.899},{"id":"20","value":0.911},{"id":"21","value":0.889},{"id":"22","value":0.866},{"id":"23","value":0.906},{"id":"24","value":0.93},{"id":"25","value":0.933},{"id":"26","value":0.908},{"id":"27","value":0.928},{"id":"28","value":0.839},{"id":"29","value":0.897},{"id":"30","value":0.9},{"id":"31","value":0.918},{"id":"32","value":0.911},{"id":"33","value":0.936},{"id":"34","value":0.928},{"id":"35","value":0.844},{"id":"36","value":0.906},{"id":"37","value":0.898},{"id":"38","value":0.896},{"id":"39","value":0.905},{"id":"40","value":0.887},{"id":"41","value":0.93},{"id":"42","value":0.903},{"id":"44","value":0.922},{"id":"45","value":0.88},{"id":"46","value":0.893},{"id":"47","value":0.889},{"id":"48","value":0.904},{"id":"49","value":0.942},{"id":"50","value":0.89},{"id":"51","value":0.914},{"id":"53","value":0.943},{"id":"54","value":0.866},{"id":"55","value":0.91},{"id":"56","value":0.91}]}
